[
  {
    "actress_name": "Vitta Quinn",
    "birthplace": "",
    "hashtag": "nude",
    "celeb_img_url": "https://cdn2.aznude.com/biopic/83969_biopic.jpg",
    "view_count": "2.4K",
    "url": "https://aznude.com/view/celeb/v/vittaquinn.html",
    "production_media_list": [
      {
        "type": "Movie",
        "title": "PASSENGER SIDE",
        "start_year": "2009",
        "end_year": null,
        "ongoing": false,
        "media_list": [
          {
            "link_to_media": "https://www.aznude.com/mrskin/vittaquinn/passengerside/passengerside-quinn-1-hi.html",
            "eid": "https://www.aznude.com/embed/passengerside-quinn-1-hi.html",
            "image_source": "https://cdn2.aznude.com/vittaquinn/passengerside/PassengerSide-Quinn-1-largeCelebPage-4.jpg",
            "type": "video"
          },
          {
            "link_to_media": "https://cdn1.aznude.com/vittaquinn/passengerside/Quinn-Passenger-n-01.jpg",
            "eid": null,
            "image_source": "https://cdn2.aznude.com/antibandit/vittaquinn/passengerside/thumb3_Quinn-Passenger-n-01.jpg",
            "type": "picture"
          },
          {
            "link_to_media": "https://cdn1.aznude.com/vittaquinn/passengerside/Quinn-Passenger-u-04.jpg",
            "eid": null,
            "image_source": "https://cdn2.aznude.com/antibandit/vittaquinn/passengerside/thumb3_Quinn-Passenger-u-04.jpg",
            "type": "picture"
          },
          {
            "link_to_media": "https://cdn1.aznude.com/vittaquinn/passengerside/Quinn-Passenger-u-03.jpg",
            "eid": null,
            "image_source": "https://cdn2.aznude.com/antibandit/vittaquinn/passengerside/thumb3_Quinn-Passenger-u-03.jpg",
            "type": "picture"
          },
          {
            "link_to_media": "https://cdn1.aznude.com/vittaquinn/passengerside/Quinn-Passenger-n-02.jpg",
            "eid": null,
            "image_source": "https://cdn2.aznude.com/antibandit/vittaquinn/passengerside/thumb3_Quinn-Passenger-n-02.jpg",
            "type": "picture"
          }
        ]
      }
    ]
  },
  {
    "actress_name": "Joanna Samojlowicz",
    "birthplace": "",
    "hashtag": "nude",
    "celeb_img_url": "https://cdn2.aznude.com/biopic/25027_biopic.jpg",
    "view_count": "2.4K",
    "url": "https://aznude.com/view/celeb/j/joannasamojlowicz.html",
    "production_media_list": [
      {
        "type": "Movie",
        "title": "THE WHITE RAVEN",
        "start_year": "1998",
        "end_year": null,
        "ongoing": false,
        "media_list": [
          {
            "link_to_media": "https://www.aznude.com/mrskin/joannasamojlowicz/thewhiteraven/whiteraven-samoslo1-hi.html",
            "eid": "https://www.aznude.com/embed/whiteraven-samoslo1-hi.html",
            "image_source": "https://cdn2.aznude.com/joannasamojlowicz/thewhiteraven/whiteraven-samoslo1-largeCelebPage-4.jpg",
            "type": "video"
          },
          {
            "link_to_media": "https://cdn1.aznude.com/joannasamojlowicz/thewhiteraven/samojlowicz-white-n-01.jpg",
            "eid": null,
            "image_source": "https://cdn2.aznude.com/antibandit/joannasamojlowicz/thewhiteraven/thumb3_samojlowicz-white-n-01.jpg",
            "type": "picture"
          },
          {
            "link_to_media": "https://cdn1.aznude.com/joannasamojlowicz/thewhiteraven/samojlowicz-white-n-04.jpg",
            "eid": null,
            "image_source": "https://cdn2.aznude.com/antibandit/joannasamojlowicz/thewhiteraven/thumb3_samojlowicz-white-n-04.jpg",
            "type": "picture"
          },
          {
            "link_to_media": "https://cdn1.aznude.com/joannasamojlowicz/thewhiteraven/samojlowicz-white-n-03.jpg",
            "eid": null,
            "image_source": "https://cdn2.aznude.com/antibandit/joannasamojlowicz/thewhiteraven/thumb3_samojlowicz-white-n-03.jpg",
            "type": "picture"
          },
          {
            "link_to_media": "https://cdn1.aznude.com/joannasamojlowicz/thewhiteraven/samojlowicz-white-n-05.jpg",
            "eid": null,
            "image_source": "https://cdn2.aznude.com/antibandit/joannasamojlowicz/thewhiteraven/thumb3_samojlowicz-white-n-05.jpg",
            "type": "picture"
          },
          {
            "link_to_media": "https://cdn1.aznude.com/joannasamojlowicz/thewhiteraven/samojlowicz-white-n-02.jpg",
            "eid": null,
            "image_source": "https://cdn2.aznude.com/antibandit/joannasamojlowicz/thewhiteraven/thumb3_samojlowicz-white-n-02.jpg",
            "type": "picture"
          }
        ]
      }
    ]
  },
  {
    "actress_name": "Elise",
    "birthplace": "",
    "hashtag": "nude",
    "celeb_img_url": "https://cdn2.aznude.com/biopic/actress_biopic_default-a7bcb7dd5a7afc9ad5e7415750030973.png",
    "view_count": "2.4K",
    "url": "https://aznude.com/view/celeb/e/elise.html",
    "production_media_list": [
      {
        "type": "Movie",
        "title": "PIMP",
        "start_year": "2010",
        "end_year": null,
        "ongoing": false,
        "media_list": [
          {
            "link_to_media": "https://www.aznude.com/mrskin/elise/pimp/pimp-cooper-1-hi.html",
            "eid": "https://www.aznude.com/embed/pimp-cooper-1-hi.html",
            "image_source": "https://cdn2.aznude.com/elise/pimp/Pimp-Cooper-1-largeCelebPage-4.jpg",
            "type": "video"
          },
          {
            "link_to_media": "https://cdn1.aznude.com/elise/pimp/Elise-Pimp-n-01.jpg",
            "eid": null,
            "image_source": "https://cdn2.aznude.com/antibandit/elise/pimp/thumb3_Elise-Pimp-n-01.jpg",
            "type": "picture"
          },
          {
            "link_to_media": "https://cdn1.aznude.com/elise/pimp/Elise-Pimp-n-02.jpg",
            "eid": null,
            "image_source": "https://cdn2.aznude.com/antibandit/elise/pimp/thumb3_Elise-Pimp-n-02.jpg",
            "type": "picture"
          }
        ]
      }
    ]
  },
  {
    "actress_name": "Monica Wadwa",
    "birthplace": "",
    "hashtag": "nude",
    "celeb_img_url": "https://cdn2.aznude.com/biopic/monica-wadwa-ad8ec588_biopic.jpg",
    "view_count": "2.4K",
    "url": "https://aznude.com/view/celeb/m/monicawadwa.html",
    "production_media_list": [
      {
        "type": "Movie",
        "title": "THE GENERATOR",
        "start_year": "2017",
        "end_year": null,
        "ongoing": false,
        "media_list": [
          {
            "link_to_media": "https://cdn2.aznude.com/monicawadwa/thegenerator/monica_wadwa_9314f2.jpg",
            "eid": null,
            "image_source": "https://cdn2.aznude.com/antibandit/monicawadwa/thegenerator/thumb3_monica_wadwa_9314f2.jpg",
            "type": "picture"
          },
          {
            "link_to_media": "https://cdn2.aznude.com/monicawadwa/thegenerator/monica_wadwa_a253a8.jpg",
            "eid": null,
            "image_source": "https://cdn2.aznude.com/antibandit/monicawadwa/thegenerator/thumb3_monica_wadwa_a253a8.jpg",
            "type": "picture"
          }
        ]
      }
    ]
  },
  {
    "actress_name": "Maja Campar",
    "birthplace": "Serbia",
    "hashtag": "nude",
    "celeb_img_url": "https://cdn2.aznude.com/biopic/aznceleb-4006151_biopic.jpg",
    "view_count": "2.4K",
    "url": "https://aznude.com/view/celeb/m/majacampar.html",
    "production_media_list": [
      {
        "type": "Movie",
        "title": "GUARDIANS OF THE FORMULA",
        "start_year": "2023",
        "end_year": null,
        "ongoing": false,
        "media_list": [
          {
            "link_to_media": "https://www.aznude.com/azncdn/cb99d482ded544118f054ace3c9e38c6/cb99d482ded544118f054ace3c9e38c6-hd.html",
            "eid": "https://www.aznude.com/embed/cb99d482ded544118f054ace3c9e38c6-hd.html",
            "image_source": "https://cdn2.aznude.com/cb99d482ded544118f054ace3c9e38c6/cb99d482ded544118f054ace3c9e38c6-largeCelebPage-4.jpg",
            "type": "video"
          },
          {
            "link_to_media": "https://cdn2.aznude.com/499abc5dd00e4652a7fd79533c7d2f0c/499abc5dd00e4652a7fd79533c7d2f0c.jpg",
            "eid": null,
            "image_source": "https://cdn2.aznude.com/antibandit/499abc5dd00e4652a7fd79533c7d2f0c/thumb3_499abc5dd00e4652a7fd79533c7d2f0c.jpg",
            "type": "picture"
          },
          {
            "link_to_media": "https://cdn2.aznude.com/b3c658ded68745e980696d3177560e7c/b3c658ded68745e980696d3177560e7c.jpg",
            "eid": null,
            "image_source": "https://cdn2.aznude.com/antibandit/b3c658ded68745e980696d3177560e7c/thumb3_b3c658ded68745e980696d3177560e7c.jpg",
            "type": "picture"
          },
          {
            "link_to_media": "https://cdn2.aznude.com/1da9871bc01147e2b8f855e8fbd19dd7/1da9871bc01147e2b8f855e8fbd19dd7.jpg",
            "eid": null,
            "image_source": "https://cdn2.aznude.com/antibandit/1da9871bc01147e2b8f855e8fbd19dd7/thumb3_1da9871bc01147e2b8f855e8fbd19dd7.jpg",
            "type": "picture"
          },
          {
            "link_to_media": "https://cdn2.aznude.com/53135e8ca07f4047b12c713f08f5f542/53135e8ca07f4047b12c713f08f5f542.jpg",
            "eid": null,
            "image_source": "https://cdn2.aznude.com/antibandit/53135e8ca07f4047b12c713f08f5f542/thumb3_53135e8ca07f4047b12c713f08f5f542.jpg",
            "type": "picture"
          },
          {
            "link_to_media": "https://cdn2.aznude.com/0253989a957440f19247fe9aa51cb65c/0253989a957440f19247fe9aa51cb65c.jpg",
            "eid": null,
            "image_source": "https://cdn2.aznude.com/antibandit/0253989a957440f19247fe9aa51cb65c/thumb3_0253989a957440f19247fe9aa51cb65c.jpg",
            "type": "picture"
          }
        ]
      },
      {
        "type": "Movie",
        "title": "VREME ZLA",
        "start_year": "2021",
        "end_year": null,
        "ongoing": false,
        "media_list": [
          {
            "link_to_media": "https://www.aznude.com/azncdn/bdc8db82e0664b0e8aa1ad6ab0057dfd/bdc8db82e0664b0e8aa1ad6ab0057dfd-hd.html",
            "eid": "https://www.aznude.com/embed/bdc8db82e0664b0e8aa1ad6ab0057dfd-hd.html",
            "image_source": "https://cdn2.aznude.com/bdc8db82e0664b0e8aa1ad6ab0057dfd/bdc8db82e0664b0e8aa1ad6ab0057dfd-largeCelebPage-4.jpg",
            "type": "video"
          },
          {
            "link_to_media": "https://cdn2.aznude.com/b898024b3a1f4f3cab0ccb883f085175/b898024b3a1f4f3cab0ccb883f085175.jpg",
            "eid": null,
            "image_source": "https://cdn2.aznude.com/antibandit/b898024b3a1f4f3cab0ccb883f085175/thumb3_b898024b3a1f4f3cab0ccb883f085175.jpg",
            "type": "picture"
          },
          {
            "link_to_media": "https://cdn2.aznude.com/f1e616fe3347426da812214adc1dc1e4/f1e616fe3347426da812214adc1dc1e4.jpg",
            "eid": null,
            "image_source": "https://cdn2.aznude.com/antibandit/f1e616fe3347426da812214adc1dc1e4/thumb3_f1e616fe3347426da812214adc1dc1e4.jpg",
            "type": "picture"
          },
          {
            "link_to_media": "https://cdn2.aznude.com/0a96ce31818f451a94df77884230b25a/0a96ce31818f451a94df77884230b25a.jpg",
            "eid": null,
            "image_source": "https://cdn2.aznude.com/antibandit/0a96ce31818f451a94df77884230b25a/thumb3_0a96ce31818f451a94df77884230b25a.jpg",
            "type": "picture"
          },
          {
            "link_to_media": "https://cdn2.aznude.com/1f0dd31e68274f0498daf6ffd38d2e65/1f0dd31e68274f0498daf6ffd38d2e65.jpg",
            "eid": null,
            "image_source": "https://cdn2.aznude.com/antibandit/1f0dd31e68274f0498daf6ffd38d2e65/thumb3_1f0dd31e68274f0498daf6ffd38d2e65.jpg",
            "type": "picture"
          },
          {
            "link_to_media": "https://cdn2.aznude.com/265bf47070d940c28057ffa4aeda0bdd/265bf47070d940c28057ffa4aeda0bdd.jpg",
            "eid": null,
            "image_source": "https://cdn2.aznude.com/antibandit/265bf47070d940c28057ffa4aeda0bdd/thumb3_265bf47070d940c28057ffa4aeda0bdd.jpg",
            "type": "picture"
          },
          {
            "link_to_media": "https://cdn2.aznude.com/b83e4626c17d431b871603338fdb5aa2/b83e4626c17d431b871603338fdb5aa2.jpg",
            "eid": null,
            "image_source": "https://cdn2.aznude.com/antibandit/b83e4626c17d431b871603338fdb5aa2/thumb3_b83e4626c17d431b871603338fdb5aa2.jpg",
            "type": "picture"
          },
          {
            "link_to_media": "https://cdn2.aznude.com/5b03b8a761a44f069e2b188f699b1cc3/5b03b8a761a44f069e2b188f699b1cc3.jpg",
            "eid": null,
            "image_source": "https://cdn2.aznude.com/antibandit/5b03b8a761a44f069e2b188f699b1cc3/thumb3_5b03b8a761a44f069e2b188f699b1cc3.jpg",
            "type": "picture"
          },
          {
            "link_to_media": "https://cdn2.aznude.com/77107312ca0c4c8baaff4f6eebe49805/77107312ca0c4c8baaff4f6eebe49805.jpg",
            "eid": null,
            "image_source": "https://cdn2.aznude.com/antibandit/77107312ca0c4c8baaff4f6eebe49805/thumb3_77107312ca0c4c8baaff4f6eebe49805.jpg",
            "type": "picture"
          },
          {
            "link_to_media": "https://cdn2.aznude.com/8c4708e43a324018ab76f2277b07a289/8c4708e43a324018ab76f2277b07a289.jpg",
            "eid": null,
            "image_source": "https://cdn2.aznude.com/antibandit/8c4708e43a324018ab76f2277b07a289/thumb3_8c4708e43a324018ab76f2277b07a289.jpg",
            "type": "picture"
          },
          {
            "link_to_media": "https://cdn2.aznude.com/8f78c34c0dd14e23b86f8958c3933ec1/8f78c34c0dd14e23b86f8958c3933ec1.jpg",
            "eid": null,
            "image_source": "https://cdn2.aznude.com/antibandit/8f78c34c0dd14e23b86f8958c3933ec1/thumb3_8f78c34c0dd14e23b86f8958c3933ec1.jpg",
            "type": "picture"
          },
          {
            "link_to_media": "https://cdn2.aznude.com/fea568ce392e477b88dc7a86d6a271eb/fea568ce392e477b88dc7a86d6a271eb.jpg",
            "eid": null,
            "image_source": "https://cdn2.aznude.com/antibandit/fea568ce392e477b88dc7a86d6a271eb/thumb3_fea568ce392e477b88dc7a86d6a271eb.jpg",
            "type": "picture"
          },
          {
            "link_to_media": "https://cdn2.aznude.com/1d9dfeab19a141a7811cbbcdcf5ad8fd/1d9dfeab19a141a7811cbbcdcf5ad8fd.jpg",
            "eid": null,
            "image_source": "https://cdn2.aznude.com/antibandit/1d9dfeab19a141a7811cbbcdcf5ad8fd/thumb3_1d9dfeab19a141a7811cbbcdcf5ad8fd.jpg",
            "type": "picture"
          }
        ]
      }
    ]
  },
  {
    "actress_name": "Shayna Terese Taylor",
    "birthplace": "",
    "hashtag": "nude",
    "celeb_img_url": "https://cdn2.aznude.com/biopic/story_celeb_1528489619-411079108.jpg",
    "view_count": "2.4K",
    "url": "https://aznude.com/view/celeb/s/shaynateresetaylor.html",
    "production_media_list": [
      {
        "type": "Story",
        "title": "SHAYNA TERESE TAYLOR SEXY ON THE BEACH IN MEXICO",
        "start_year": "2021",
        "end_year": null,
        "ongoing": false,
        "media_list": []
      },
      {
        "type": "Story",
        "title": "SHAYNA TERESE TAYLOR SEXY ENJOYING A DAY ON THE BEACH IN BLUE BIKINI IN TULUM, MEXICO",
        "start_year": "2021",
        "end_year": null,
        "ongoing": false,
        "media_list": []
      },
      {
        "type": "Story",
        "title": "SHAYNA TERESE TAYLOR SEXY AT THE BEACH IN TULUM WITH HER MOTHER (17.05.2019)",
        "start_year": "2019",
        "end_year": null,
        "ongoing": false,
        "media_list": []
      },
      {
        "type": "Story",
        "title": "SHAYNA TERESE TAYLOR AND RYAN SEACREST PICTURED BACK TOGETHER AND LOOKING HAPPY ON THEIR HOLIDAY IN POSITANO",
        "start_year": "2019",
        "end_year": null,
        "ongoing": false,
        "media_list": []
      },
      {
        "type": "Story",
        "title": "SHAYNA TAYLOR AND RYAN SEACREST PICTURED ENJOYING THEIR SUMMER VACATION IN POSITANO, ITALY WITH FRIENDS",
        "start_year": "2019",
        "end_year": null,
        "ongoing": false,
        "media_list": []
      },
      {
        "type": "Story",
        "title": "SHAYNA TERESE TAYLOR VACATIONING ON THE BEACH IN TULUM MEXICO",
        "start_year": "2018",
        "end_year": null,
        "ongoing": false,
        "media_list": []
      },
      {
        "type": "Story",
        "title": "SHAYNA TERESE TAYLOR SEXY ON THE BEACH IN TULUM MEXICO",
        "start_year": "2018",
        "end_year": null,
        "ongoing": false,
        "media_list": []
      },
      {
        "type": "Story",
        "title": "SHAYNA TERESE TAYLOR SEXY FOR THE VICTORIA'S SECRET FASHION SHOW 2018 IN MIDTOWN IN NEW YORK CITY",
        "start_year": "2018",
        "end_year": null,
        "ongoing": false,
        "media_list": []
      },
      {
        "type": "Story",
        "title": "SHAYNA TERESE TAYLOR SEXY AT THE POOL WITH RYAN SEACREST IN MIAMI",
        "start_year": "2017",
        "end_year": null,
        "ongoing": false,
        "media_list": []
      },
      {
        "type": "Story",
        "title": "SHAYNA TERESE TAYLOR TOPLESS PAPARAZZI PHOTOS",
        "start_year": "2015",
        "end_year": null,
        "ongoing": false,
        "media_list": []
      }
    ]
  },
  {
    "actress_name": "Malorie Woods",
    "birthplace": "",
    "hashtag": "nude",
    "celeb_img_url": "https://cdn2.aznude.com/biopic/story_celeb_1600987345-363521076.jpg",
    "view_count": "2.4K",
    "url": "https://aznude.com/view/celeb/m/maloriewoods.html",
    "production_media_list": []
  },
  {
    "actress_name": "Pauline Delpech",
    "birthplace": "France",
    "hashtag": "nude",
    "celeb_img_url": "https://cdn2.aznude.com/biopic/aznceleb-4008567_biopic.jpg",
    "view_count": "2.4K",
    "url": "https://aznude.com/view/celeb/p/paulinedelpech.html",
    "production_media_list": [
      {
        "type": "Movie",
        "title": "LE CANCER DU SEIN, PARLONS EN !",
        "start_year": "2012",
        "end_year": null,
        "ongoing": false,
        "media_list": [
          {
            "link_to_media": "https://www.aznude.com/azncdn/6d0a4b0e9e4e4a038d023d563502e694/6d0a4b0e9e4e4a038d023d563502e694-hd.html",
            "eid": "https://www.aznude.com/embed/6d0a4b0e9e4e4a038d023d563502e694-hd.html",
            "image_source": "https://cdn2.aznude.com/6d0a4b0e9e4e4a038d023d563502e694/6d0a4b0e9e4e4a038d023d563502e694-largeCelebPage-4.jpg",
            "type": "video"
          },
          {
            "link_to_media": "https://cdn2.aznude.com/6a8ae30c9d52432d8b15818d7e4e99a1/6a8ae30c9d52432d8b15818d7e4e99a1.jpg",
            "eid": null,
            "image_source": "https://cdn2.aznude.com/antibandit/6a8ae30c9d52432d8b15818d7e4e99a1/thumb3_6a8ae30c9d52432d8b15818d7e4e99a1.jpg",
            "type": "picture"
          },
          {
            "link_to_media": "https://cdn2.aznude.com/9aaf04ffaec0418188503d34163d345a/9aaf04ffaec0418188503d34163d345a.jpg",
            "eid": null,
            "image_source": "https://cdn2.aznude.com/antibandit/9aaf04ffaec0418188503d34163d345a/thumb3_9aaf04ffaec0418188503d34163d345a.jpg",
            "type": "picture"
          },
          {
            "link_to_media": "https://cdn2.aznude.com/b52ec3862dad46baa7f183cd59f91802/b52ec3862dad46baa7f183cd59f91802.jpg",
            "eid": null,
            "image_source": "https://cdn2.aznude.com/antibandit/b52ec3862dad46baa7f183cd59f91802/thumb3_b52ec3862dad46baa7f183cd59f91802.jpg",
            "type": "picture"
          },
          {
            "link_to_media": "https://cdn2.aznude.com/87a16ee74f274ac0a9dbb3dedeae2241/87a16ee74f274ac0a9dbb3dedeae2241.jpg",
            "eid": null,
            "image_source": "https://cdn2.aznude.com/antibandit/87a16ee74f274ac0a9dbb3dedeae2241/thumb3_87a16ee74f274ac0a9dbb3dedeae2241.jpg",
            "type": "picture"
          },
          {
            "link_to_media": "https://cdn2.aznude.com/0dac4480a59546b1b421d8422214f766/0dac4480a59546b1b421d8422214f766.jpg",
            "eid": null,
            "image_source": "https://cdn2.aznude.com/antibandit/0dac4480a59546b1b421d8422214f766/thumb3_0dac4480a59546b1b421d8422214f766.jpg",
            "type": "picture"
          },
          {
            "link_to_media": "https://cdn2.aznude.com/46629b6348cb4d039b39ea786c30c1d5/46629b6348cb4d039b39ea786c30c1d5.jpg",
            "eid": null,
            "image_source": "https://cdn2.aznude.com/antibandit/46629b6348cb4d039b39ea786c30c1d5/thumb3_46629b6348cb4d039b39ea786c30c1d5.jpg",
            "type": "picture"
          },
          {
            "link_to_media": "https://cdn2.aznude.com/add8ed39d46447f28a77e3caf202a210/add8ed39d46447f28a77e3caf202a210.jpg",
            "eid": null,
            "image_source": "https://cdn2.aznude.com/antibandit/add8ed39d46447f28a77e3caf202a210/thumb3_add8ed39d46447f28a77e3caf202a210.jpg",
            "type": "picture"
          },
          {
            "link_to_media": "https://cdn2.aznude.com/acd77587166f4b41a1a69e50b5d1d07e/acd77587166f4b41a1a69e50b5d1d07e.jpg",
            "eid": null,
            "image_source": "https://cdn2.aznude.com/antibandit/acd77587166f4b41a1a69e50b5d1d07e/thumb3_acd77587166f4b41a1a69e50b5d1d07e.jpg",
            "type": "picture"
          },
          {
            "link_to_media": "https://cdn2.aznude.com/4f87e4e8e3404697bab10b768a54e70b/4f87e4e8e3404697bab10b768a54e70b.jpg",
            "eid": null,
            "image_source": "https://cdn2.aznude.com/antibandit/4f87e4e8e3404697bab10b768a54e70b/thumb3_4f87e4e8e3404697bab10b768a54e70b.jpg",
            "type": "picture"
          },
          {
            "link_to_media": "https://cdn2.aznude.com/406e2a91fbf94d75a7545de7eedebb04/406e2a91fbf94d75a7545de7eedebb04.jpg",
            "eid": null,
            "image_source": "https://cdn2.aznude.com/antibandit/406e2a91fbf94d75a7545de7eedebb04/thumb3_406e2a91fbf94d75a7545de7eedebb04.jpg",
            "type": "picture"
          },
          {
            "link_to_media": "https://cdn2.aznude.com/4ef1157a5ac243d49b52218eb8c931cd/4ef1157a5ac243d49b52218eb8c931cd.jpg",
            "eid": null,
            "image_source": "https://cdn2.aznude.com/antibandit/4ef1157a5ac243d49b52218eb8c931cd/thumb3_4ef1157a5ac243d49b52218eb8c931cd.jpg",
            "type": "picture"
          },
          {
            "link_to_media": "https://cdn2.aznude.com/d29111b36ee349b9b72ff871c2bc0a1c/d29111b36ee349b9b72ff871c2bc0a1c.jpg",
            "eid": null,
            "image_source": "https://cdn2.aznude.com/antibandit/d29111b36ee349b9b72ff871c2bc0a1c/thumb3_d29111b36ee349b9b72ff871c2bc0a1c.jpg",
            "type": "picture"
          },
          {
            "link_to_media": "https://cdn2.aznude.com/3451815367294cfc969379693a026d19/3451815367294cfc969379693a026d19.jpg",
            "eid": null,
            "image_source": "https://cdn2.aznude.com/antibandit/3451815367294cfc969379693a026d19/thumb3_3451815367294cfc969379693a026d19.jpg",
            "type": "picture"
          },
          {
            "link_to_media": "https://cdn2.aznude.com/2edef6a6f5af44e698f6608adf7e6607/2edef6a6f5af44e698f6608adf7e6607.jpg",
            "eid": null,
            "image_source": "https://cdn2.aznude.com/antibandit/2edef6a6f5af44e698f6608adf7e6607/thumb3_2edef6a6f5af44e698f6608adf7e6607.jpg",
            "type": "picture"
          },
          {
            "link_to_media": "https://cdn2.aznude.com/896205bfe4f440bb90656bfd667453d4/896205bfe4f440bb90656bfd667453d4.jpg",
            "eid": null,
            "image_source": "https://cdn2.aznude.com/antibandit/896205bfe4f440bb90656bfd667453d4/thumb3_896205bfe4f440bb90656bfd667453d4.jpg",
            "type": "picture"
          },
          {
            "link_to_media": "https://cdn2.aznude.com/6a783bd4f905423fb5413f1981af323f/6a783bd4f905423fb5413f1981af323f.jpg",
            "eid": null,
            "image_source": "https://cdn2.aznude.com/antibandit/6a783bd4f905423fb5413f1981af323f/thumb3_6a783bd4f905423fb5413f1981af323f.jpg",
            "type": "picture"
          },
          {
            "link_to_media": "https://cdn2.aznude.com/1639456018054d0da89cc8327c455d04/1639456018054d0da89cc8327c455d04.jpg",
            "eid": null,
            "image_source": "https://cdn2.aznude.com/antibandit/1639456018054d0da89cc8327c455d04/thumb3_1639456018054d0da89cc8327c455d04.jpg",
            "type": "picture"
          },
          {
            "link_to_media": "https://cdn2.aznude.com/fbb5da8042a54914a2195096993269e1/fbb5da8042a54914a2195096993269e1.jpg",
            "eid": null,
            "image_source": "https://cdn2.aznude.com/antibandit/fbb5da8042a54914a2195096993269e1/thumb3_fbb5da8042a54914a2195096993269e1.jpg",
            "type": "picture"
          },
          {
            "link_to_media": "https://cdn2.aznude.com/7b36e0bbdcd44d56a982128e350e2a40/7b36e0bbdcd44d56a982128e350e2a40.jpg",
            "eid": null,
            "image_source": "https://cdn2.aznude.com/antibandit/7b36e0bbdcd44d56a982128e350e2a40/thumb3_7b36e0bbdcd44d56a982128e350e2a40.jpg",
            "type": "picture"
          },
          {
            "link_to_media": "https://cdn2.aznude.com/a7539ea2b84146b9829703f7fb9496f8/a7539ea2b84146b9829703f7fb9496f8.jpg",
            "eid": null,
            "image_source": "https://cdn2.aznude.com/antibandit/a7539ea2b84146b9829703f7fb9496f8/thumb3_a7539ea2b84146b9829703f7fb9496f8.jpg",
            "type": "picture"
          },
          {
            "link_to_media": "https://cdn2.aznude.com/e6ebeafb6f8245f5b505af970488b00b/e6ebeafb6f8245f5b505af970488b00b.jpg",
            "eid": null,
            "image_source": "https://cdn2.aznude.com/antibandit/e6ebeafb6f8245f5b505af970488b00b/thumb3_e6ebeafb6f8245f5b505af970488b00b.jpg",
            "type": "picture"
          },
          {
            "link_to_media": "https://cdn2.aznude.com/26fa2ad138104a46aa3cde471c2d63df/26fa2ad138104a46aa3cde471c2d63df.jpg",
            "eid": null,
            "image_source": "https://cdn2.aznude.com/antibandit/26fa2ad138104a46aa3cde471c2d63df/thumb3_26fa2ad138104a46aa3cde471c2d63df.jpg",
            "type": "picture"
          },
          {
            "link_to_media": "https://cdn2.aznude.com/3d4108d992a54c63a2c578db27b3fe47/3d4108d992a54c63a2c578db27b3fe47.jpg",
            "eid": null,
            "image_source": "https://cdn2.aznude.com/antibandit/3d4108d992a54c63a2c578db27b3fe47/thumb3_3d4108d992a54c63a2c578db27b3fe47.jpg",
            "type": "picture"
          },
          {
            "link_to_media": "https://cdn2.aznude.com/0fa09c35dc7146d69ac5930230b608e6/0fa09c35dc7146d69ac5930230b608e6.jpg",
            "eid": null,
            "image_source": "https://cdn2.aznude.com/antibandit/0fa09c35dc7146d69ac5930230b608e6/thumb3_0fa09c35dc7146d69ac5930230b608e6.jpg",
            "type": "picture"
          },
          {
            "link_to_media": "https://cdn2.aznude.com/e5e3fc3176484d80a67be041822c354d/e5e3fc3176484d80a67be041822c354d.jpg",
            "eid": null,
            "image_source": "https://cdn2.aznude.com/antibandit/e5e3fc3176484d80a67be041822c354d/thumb3_e5e3fc3176484d80a67be041822c354d.jpg",
            "type": "picture"
          },
          {
            "link_to_media": "https://cdn2.aznude.com/b0b39dcf511c4b289c032bc42c9f74d0/b0b39dcf511c4b289c032bc42c9f74d0.jpg",
            "eid": null,
            "image_source": "https://cdn2.aznude.com/antibandit/b0b39dcf511c4b289c032bc42c9f74d0/thumb3_b0b39dcf511c4b289c032bc42c9f74d0.jpg",
            "type": "picture"
          },
          {
            "link_to_media": "https://cdn2.aznude.com/d3b1e71de07b4895b8e17d0dc436cc8c/d3b1e71de07b4895b8e17d0dc436cc8c.jpg",
            "eid": null,
            "image_source": "https://cdn2.aznude.com/antibandit/d3b1e71de07b4895b8e17d0dc436cc8c/thumb3_d3b1e71de07b4895b8e17d0dc436cc8c.jpg",
            "type": "picture"
          },
          {
            "link_to_media": "https://cdn2.aznude.com/8ced28939b4f494d95d205cbe4504e91/8ced28939b4f494d95d205cbe4504e91.jpg",
            "eid": null,
            "image_source": "https://cdn2.aznude.com/antibandit/8ced28939b4f494d95d205cbe4504e91/thumb3_8ced28939b4f494d95d205cbe4504e91.jpg",
            "type": "picture"
          },
          {
            "link_to_media": "https://cdn2.aznude.com/8a4fdb25f65f445fb4b22130ef6793e4/8a4fdb25f65f445fb4b22130ef6793e4.jpg",
            "eid": null,
            "image_source": "https://cdn2.aznude.com/antibandit/8a4fdb25f65f445fb4b22130ef6793e4/thumb3_8a4fdb25f65f445fb4b22130ef6793e4.jpg",
            "type": "picture"
          },
          {
            "link_to_media": "https://cdn2.aznude.com/05e3a4c9ac554e42af39161c29249eb6/05e3a4c9ac554e42af39161c29249eb6.jpg",
            "eid": null,
            "image_source": "https://cdn2.aznude.com/antibandit/05e3a4c9ac554e42af39161c29249eb6/thumb3_05e3a4c9ac554e42af39161c29249eb6.jpg",
            "type": "picture"
          },
          {
            "link_to_media": "https://cdn2.aznude.com/47ac0bbf783b4e6190ff5b6e1afd69c9/47ac0bbf783b4e6190ff5b6e1afd69c9.jpg",
            "eid": null,
            "image_source": "https://cdn2.aznude.com/antibandit/47ac0bbf783b4e6190ff5b6e1afd69c9/thumb3_47ac0bbf783b4e6190ff5b6e1afd69c9.jpg",
            "type": "picture"
          },
          {
            "link_to_media": "https://cdn2.aznude.com/221086b46f4c4f6783fa6d35e561cac2/221086b46f4c4f6783fa6d35e561cac2.jpg",
            "eid": null,
            "image_source": "https://cdn2.aznude.com/antibandit/221086b46f4c4f6783fa6d35e561cac2/thumb3_221086b46f4c4f6783fa6d35e561cac2.jpg",
            "type": "picture"
          },
          {
            "link_to_media": "https://cdn2.aznude.com/5b39f531e1904f178c3c4c0a2a54e8c4/5b39f531e1904f178c3c4c0a2a54e8c4.jpg",
            "eid": null,
            "image_source": "https://cdn2.aznude.com/antibandit/5b39f531e1904f178c3c4c0a2a54e8c4/thumb3_5b39f531e1904f178c3c4c0a2a54e8c4.jpg",
            "type": "picture"
          },
          {
            "link_to_media": "https://cdn2.aznude.com/5b662c06f71041b59cb6655509c0f717/5b662c06f71041b59cb6655509c0f717.jpg",
            "eid": null,
            "image_source": "https://cdn2.aznude.com/antibandit/5b662c06f71041b59cb6655509c0f717/thumb3_5b662c06f71041b59cb6655509c0f717.jpg",
            "type": "picture"
          },
          {
            "link_to_media": "https://cdn2.aznude.com/4e02c3cce4654d449111f84d09b3dd06/4e02c3cce4654d449111f84d09b3dd06.jpg",
            "eid": null,
            "image_source": "https://cdn2.aznude.com/antibandit/4e02c3cce4654d449111f84d09b3dd06/thumb3_4e02c3cce4654d449111f84d09b3dd06.jpg",
            "type": "picture"
          },
          {
            "link_to_media": "https://cdn2.aznude.com/05bdb5d3b47a43408e7ee00251211611/05bdb5d3b47a43408e7ee00251211611.jpg",
            "eid": null,
            "image_source": "https://cdn2.aznude.com/antibandit/05bdb5d3b47a43408e7ee00251211611/thumb3_05bdb5d3b47a43408e7ee00251211611.jpg",
            "type": "picture"
          },
          {
            "link_to_media": "https://cdn2.aznude.com/9b29cf89029c40d0b8b34b5e2a95a046/9b29cf89029c40d0b8b34b5e2a95a046.jpg",
            "eid": null,
            "image_source": "https://cdn2.aznude.com/antibandit/9b29cf89029c40d0b8b34b5e2a95a046/thumb3_9b29cf89029c40d0b8b34b5e2a95a046.jpg",
            "type": "picture"
          },
          {
            "link_to_media": "https://cdn2.aznude.com/ed9ddb1c60cd4837b091fa651408a255/ed9ddb1c60cd4837b091fa651408a255.jpg",
            "eid": null,
            "image_source": "https://cdn2.aznude.com/antibandit/ed9ddb1c60cd4837b091fa651408a255/thumb3_ed9ddb1c60cd4837b091fa651408a255.jpg",
            "type": "picture"
          },
          {
            "link_to_media": "https://cdn2.aznude.com/67782ec212ec49a4bb7dbae8143aa3de/67782ec212ec49a4bb7dbae8143aa3de.jpg",
            "eid": null,
            "image_source": "https://cdn2.aznude.com/antibandit/67782ec212ec49a4bb7dbae8143aa3de/thumb3_67782ec212ec49a4bb7dbae8143aa3de.jpg",
            "type": "picture"
          },
          {
            "link_to_media": "https://cdn2.aznude.com/8f24f64464f142af9095e7c0b4f2d3f0/8f24f64464f142af9095e7c0b4f2d3f0.jpg",
            "eid": null,
            "image_source": "https://cdn2.aznude.com/antibandit/8f24f64464f142af9095e7c0b4f2d3f0/thumb3_8f24f64464f142af9095e7c0b4f2d3f0.jpg",
            "type": "picture"
          },
          {
            "link_to_media": "https://cdn2.aznude.com/29d21920521746bda9ae1cbd9f390b6a/29d21920521746bda9ae1cbd9f390b6a.jpg",
            "eid": null,
            "image_source": "https://cdn2.aznude.com/antibandit/29d21920521746bda9ae1cbd9f390b6a/thumb3_29d21920521746bda9ae1cbd9f390b6a.jpg",
            "type": "picture"
          },
          {
            "link_to_media": "https://cdn2.aznude.com/4a5ec3ee11f64a4e863b4642c48f7b80/4a5ec3ee11f64a4e863b4642c48f7b80.jpg",
            "eid": null,
            "image_source": "https://cdn2.aznude.com/antibandit/4a5ec3ee11f64a4e863b4642c48f7b80/thumb3_4a5ec3ee11f64a4e863b4642c48f7b80.jpg",
            "type": "picture"
          },
          {
            "link_to_media": "https://cdn2.aznude.com/44ce261f9bc446729a61b21b622de26a/44ce261f9bc446729a61b21b622de26a.jpg",
            "eid": null,
            "image_source": "https://cdn2.aznude.com/antibandit/44ce261f9bc446729a61b21b622de26a/thumb3_44ce261f9bc446729a61b21b622de26a.jpg",
            "type": "picture"
          },
          {
            "link_to_media": "https://cdn2.aznude.com/ca17eada575a4f41aad37de01a19b551/ca17eada575a4f41aad37de01a19b551.jpg",
            "eid": null,
            "image_source": "https://cdn2.aznude.com/antibandit/ca17eada575a4f41aad37de01a19b551/thumb3_ca17eada575a4f41aad37de01a19b551.jpg",
            "type": "picture"
          },
          {
            "link_to_media": "https://cdn2.aznude.com/e94325a2c33249e5a847e54a9c4b319d/e94325a2c33249e5a847e54a9c4b319d.jpg",
            "eid": null,
            "image_source": "https://cdn2.aznude.com/antibandit/e94325a2c33249e5a847e54a9c4b319d/thumb3_e94325a2c33249e5a847e54a9c4b319d.jpg",
            "type": "picture"
          },
          {
            "link_to_media": "https://cdn2.aznude.com/8a48885057794a7bb76b2e04e12208fb/8a48885057794a7bb76b2e04e12208fb.jpg",
            "eid": null,
            "image_source": "https://cdn2.aznude.com/antibandit/8a48885057794a7bb76b2e04e12208fb/thumb3_8a48885057794a7bb76b2e04e12208fb.jpg",
            "type": "picture"
          },
          {
            "link_to_media": "https://cdn2.aznude.com/7e659e624f4d4949af3046d4accd804b/7e659e624f4d4949af3046d4accd804b.jpg",
            "eid": null,
            "image_source": "https://cdn2.aznude.com/antibandit/7e659e624f4d4949af3046d4accd804b/thumb3_7e659e624f4d4949af3046d4accd804b.jpg",
            "type": "picture"
          },
          {
            "link_to_media": "https://cdn2.aznude.com/a359710531d74dd5a68b52ded98cf32e/a359710531d74dd5a68b52ded98cf32e.jpg",
            "eid": null,
            "image_source": "https://cdn2.aznude.com/antibandit/a359710531d74dd5a68b52ded98cf32e/thumb3_a359710531d74dd5a68b52ded98cf32e.jpg",
            "type": "picture"
          },
          {
            "link_to_media": "https://cdn2.aznude.com/5df9df8213c24311aeb66f8fdb622bbf/5df9df8213c24311aeb66f8fdb622bbf.jpg",
            "eid": null,
            "image_source": "https://cdn2.aznude.com/antibandit/5df9df8213c24311aeb66f8fdb622bbf/thumb3_5df9df8213c24311aeb66f8fdb622bbf.jpg",
            "type": "picture"
          },
          {
            "link_to_media": "https://cdn2.aznude.com/522b6ae7d0a94c6aae2d59e1e2999c17/522b6ae7d0a94c6aae2d59e1e2999c17.jpg",
            "eid": null,
            "image_source": "https://cdn2.aznude.com/antibandit/522b6ae7d0a94c6aae2d59e1e2999c17/thumb3_522b6ae7d0a94c6aae2d59e1e2999c17.jpg",
            "type": "picture"
          },
          {
            "link_to_media": "https://cdn2.aznude.com/d6722c5c365a4c1086c8dd63d515af5d/d6722c5c365a4c1086c8dd63d515af5d.jpg",
            "eid": null,
            "image_source": "https://cdn2.aznude.com/antibandit/d6722c5c365a4c1086c8dd63d515af5d/thumb3_d6722c5c365a4c1086c8dd63d515af5d.jpg",
            "type": "picture"
          },
          {
            "link_to_media": "https://cdn2.aznude.com/1aeb16d375b9474381ddd0fbd992d73f/1aeb16d375b9474381ddd0fbd992d73f.jpg",
            "eid": null,
            "image_source": "https://cdn2.aznude.com/antibandit/1aeb16d375b9474381ddd0fbd992d73f/thumb3_1aeb16d375b9474381ddd0fbd992d73f.jpg",
            "type": "picture"
          },
          {
            "link_to_media": "https://cdn2.aznude.com/680490bf960a4fc99c9b377da4999fcd/680490bf960a4fc99c9b377da4999fcd.jpg",
            "eid": null,
            "image_source": "https://cdn2.aznude.com/antibandit/680490bf960a4fc99c9b377da4999fcd/thumb3_680490bf960a4fc99c9b377da4999fcd.jpg",
            "type": "picture"
          },
          {
            "link_to_media": "https://cdn2.aznude.com/4c9ecb3aa7ac4d858b5a1b5748cb9754/4c9ecb3aa7ac4d858b5a1b5748cb9754.jpg",
            "eid": null,
            "image_source": "https://cdn2.aznude.com/antibandit/4c9ecb3aa7ac4d858b5a1b5748cb9754/thumb3_4c9ecb3aa7ac4d858b5a1b5748cb9754.jpg",
            "type": "picture"
          },
          {
            "link_to_media": "https://cdn2.aznude.com/6c0b38d06ef04bc981a73049d616203e/6c0b38d06ef04bc981a73049d616203e.jpg",
            "eid": null,
            "image_source": "https://cdn2.aznude.com/antibandit/6c0b38d06ef04bc981a73049d616203e/thumb3_6c0b38d06ef04bc981a73049d616203e.jpg",
            "type": "picture"
          },
          {
            "link_to_media": "https://cdn2.aznude.com/31309fe8eda24be596ca628adfec4994/31309fe8eda24be596ca628adfec4994.jpg",
            "eid": null,
            "image_source": "https://cdn2.aznude.com/antibandit/31309fe8eda24be596ca628adfec4994/thumb3_31309fe8eda24be596ca628adfec4994.jpg",
            "type": "picture"
          },
          {
            "link_to_media": "https://cdn2.aznude.com/40e11da2c1884150b98c755171560d66/40e11da2c1884150b98c755171560d66.jpg",
            "eid": null,
            "image_source": "https://cdn2.aznude.com/antibandit/40e11da2c1884150b98c755171560d66/thumb3_40e11da2c1884150b98c755171560d66.jpg",
            "type": "picture"
          }
        ]
      }
    ]
  },
  {
    "actress_name": "Alena Pajtinkova",
    "birthplace": "Slovakia",
    "hashtag": "nude",
    "celeb_img_url": "https://cdn2.aznude.com/biopic/aznceleb-4009696_biopic.jpg",
    "view_count": "2.4K",
    "url": "https://aznude.com/view/celeb/a/alenapajtinkova.html",
    "production_media_list": [
      {
        "type": "Movie",
        "title": "NOCNY TREZOR",
        "start_year": "2011",
        "end_year": null,
        "ongoing": false,
        "media_list": [
          {
            "link_to_media": "https://www.aznude.com/azncdn/haztanrvfzwxana/haztanrvfzwxana-hd.html",
            "eid": "https://www.aznude.com/embed/haztanrvfzwxana-hd.html",
            "image_source": "https://cdn2.aznude.com/haztanrvfzwxana/haztanrvfzwxana-largeCelebPage-4.jpg",
            "type": "video"
          },
          {
            "link_to_media": "https://cdn2.aznude.com/haztanrvl5uw2z27gexgu4dh/haztanrvl5uw2z27gexgu4dh.jpg",
            "eid": null,
            "image_source": "https://cdn2.aznude.com/antibandit/haztanrvl5uw2z27gexgu4dh/thumb3_haztanrvl5uw2z27gexgu4dh.jpg",
            "type": "picture"
          },
          {
            "link_to_media": "https://cdn2.aznude.com/haztanrvl5uw2z27gixgu4dh/haztanrvl5uw2z27gixgu4dh.jpg",
            "eid": null,
            "image_source": "https://cdn2.aznude.com/antibandit/haztanrvl5uw2z27gixgu4dh/thumb3_haztanrvl5uw2z27gixgu4dh.jpg",
            "type": "picture"
          },
          {
            "link_to_media": "https://cdn2.aznude.com/haztanrvl5uw2z27gmxgu4dh/haztanrvl5uw2z27gmxgu4dh.jpg",
            "eid": null,
            "image_source": "https://cdn2.aznude.com/antibandit/haztanrvl5uw2z27gmxgu4dh/thumb3_haztanrvl5uw2z27gmxgu4dh.jpg",
            "type": "picture"
          },
          {
            "link_to_media": "https://cdn2.aznude.com/haztanrvl5uw2z27gqxgu4dh/haztanrvl5uw2z27gqxgu4dh.jpg",
            "eid": null,
            "image_source": "https://cdn2.aznude.com/antibandit/haztanrvl5uw2z27gqxgu4dh/thumb3_haztanrvl5uw2z27gqxgu4dh.jpg",
            "type": "picture"
          },
          {
            "link_to_media": "https://cdn2.aznude.com/haztanrvl5uw2z27guxgu4dh/haztanrvl5uw2z27guxgu4dh.jpg",
            "eid": null,
            "image_source": "https://cdn2.aznude.com/antibandit/haztanrvl5uw2z27guxgu4dh/thumb3_haztanrvl5uw2z27guxgu4dh.jpg",
            "type": "picture"
          },
          {
            "link_to_media": "https://cdn2.aznude.com/haztanrvl5uw2z27gyxgu4dh/haztanrvl5uw2z27gyxgu4dh.jpg",
            "eid": null,
            "image_source": "https://cdn2.aznude.com/antibandit/haztanrvl5uw2z27gyxgu4dh/thumb3_haztanrvl5uw2z27gyxgu4dh.jpg",
            "type": "picture"
          },
          {
            "link_to_media": "https://cdn2.aznude.com/haztanrvl5uw2z27g4xgu4dh/haztanrvl5uw2z27g4xgu4dh.jpg",
            "eid": null,
            "image_source": "https://cdn2.aznude.com/antibandit/haztanrvl5uw2z27g4xgu4dh/thumb3_haztanrvl5uw2z27g4xgu4dh.jpg",
            "type": "picture"
          },
          {
            "link_to_media": "https://cdn2.aznude.com/haztanrvl5uw2z27haxgu4dh/haztanrvl5uw2z27haxgu4dh.jpg",
            "eid": null,
            "image_source": "https://cdn2.aznude.com/antibandit/haztanrvl5uw2z27haxgu4dh/thumb3_haztanrvl5uw2z27haxgu4dh.jpg",
            "type": "picture"
          },
          {
            "link_to_media": "https://cdn2.aznude.com/haztanrvl5uw2z27hexgu4dh/haztanrvl5uw2z27hexgu4dh.jpg",
            "eid": null,
            "image_source": "https://cdn2.aznude.com/antibandit/haztanrvl5uw2z27hexgu4dh/thumb3_haztanrvl5uw2z27hexgu4dh.jpg",
            "type": "picture"
          },
          {
            "link_to_media": "https://cdn2.aznude.com/haztanrvl5uw2z27geyc42tqm4/haztanrvl5uw2z27geyc42tqm4.jpg",
            "eid": null,
            "image_source": "https://cdn2.aznude.com/antibandit/haztanrvl5uw2z27geyc42tqm4/thumb3_haztanrvl5uw2z27geyc42tqm4.jpg",
            "type": "picture"
          },
          {
            "link_to_media": "https://cdn2.aznude.com/haztanrvl5uw2z27geys42tqm4/haztanrvl5uw2z27geys42tqm4.jpg",
            "eid": null,
            "image_source": "https://cdn2.aznude.com/antibandit/haztanrvl5uw2z27geys42tqm4/thumb3_haztanrvl5uw2z27geys42tqm4.jpg",
            "type": "picture"
          },
          {
            "link_to_media": "https://cdn2.aznude.com/haztanrvl5uw2z27gezc42tqm4/haztanrvl5uw2z27gezc42tqm4.jpg",
            "eid": null,
            "image_source": "https://cdn2.aznude.com/antibandit/haztanrvl5uw2z27gezc42tqm4/thumb3_haztanrvl5uw2z27gezc42tqm4.jpg",
            "type": "picture"
          },
          {
            "link_to_media": "https://cdn2.aznude.com/haztanrvl5uw2z27gezs42tqm4/haztanrvl5uw2z27gezs42tqm4.jpg",
            "eid": null,
            "image_source": "https://cdn2.aznude.com/antibandit/haztanrvl5uw2z27gezs42tqm4/thumb3_haztanrvl5uw2z27gezs42tqm4.jpg",
            "type": "picture"
          },
          {
            "link_to_media": "https://cdn2.aznude.com/haztanrvl5uw2z27ge2c42tqm4/haztanrvl5uw2z27ge2c42tqm4.jpg",
            "eid": null,
            "image_source": "https://cdn2.aznude.com/antibandit/haztanrvl5uw2z27ge2c42tqm4/thumb3_haztanrvl5uw2z27ge2c42tqm4.jpg",
            "type": "picture"
          }
        ]
      }
    ]
  },
  {
    "actress_name": "Sara Klein",
    "birthplace": "",
    "hashtag": "nude",
    "celeb_img_url": "https://cdn2.aznude.com/biopic/aznceleb-4012568_biopic.jpg",
    "view_count": "2.4K",
    "url": "https://aznude.com/view/celeb/s/saraklein.html",
    "production_media_list": [
      {
        "type": "Series",
        "title": "YES NO MAYBE",
        "start_year": "2016",
        "end_year": null,
        "ongoing": false,
        "media_list": [
          {
            "link_to_media": "https://www.aznude.com/azncdn/g4zdiobwfzwxana/g4zdiobwfzwxana-hd.html",
            "eid": "https://www.aznude.com/embed/g4zdiobwfzwxana-hd.html",
            "image_source": "https://cdn2.aznude.com/g4zdiobwfzwxana/g4zdiobwfzwxana-largeCelebPage-4.jpg",
            "type": "video"
          },
          {
            "link_to_media": "https://cdn2.aznude.com/g4zdiobwl5uw2z27gexgu4dh/g4zdiobwl5uw2z27gexgu4dh.jpg",
            "eid": null,
            "image_source": "https://cdn2.aznude.com/antibandit/g4zdiobwl5uw2z27gexgu4dh/thumb3_g4zdiobwl5uw2z27gexgu4dh.jpg",
            "type": "picture"
          },
          {
            "link_to_media": "https://cdn2.aznude.com/g4zdiobwl5uw2z27gixgu4dh/g4zdiobwl5uw2z27gixgu4dh.jpg",
            "eid": null,
            "image_source": "https://cdn2.aznude.com/antibandit/g4zdiobwl5uw2z27gixgu4dh/thumb3_g4zdiobwl5uw2z27gixgu4dh.jpg",
            "type": "picture"
          },
          {
            "link_to_media": "https://cdn2.aznude.com/g4zdiobwl5uw2z27gmxgu4dh/g4zdiobwl5uw2z27gmxgu4dh.jpg",
            "eid": null,
            "image_source": "https://cdn2.aznude.com/antibandit/g4zdiobwl5uw2z27gmxgu4dh/thumb3_g4zdiobwl5uw2z27gmxgu4dh.jpg",
            "type": "picture"
          },
          {
            "link_to_media": "https://cdn2.aznude.com/g4zdiobwl5uw2z27gqxgu4dh/g4zdiobwl5uw2z27gqxgu4dh.jpg",
            "eid": null,
            "image_source": "https://cdn2.aznude.com/antibandit/g4zdiobwl5uw2z27gqxgu4dh/thumb3_g4zdiobwl5uw2z27gqxgu4dh.jpg",
            "type": "picture"
          },
          {
            "link_to_media": "https://cdn2.aznude.com/g4zdiobwl5uw2z27guxgu4dh/g4zdiobwl5uw2z27guxgu4dh.jpg",
            "eid": null,
            "image_source": "https://cdn2.aznude.com/antibandit/g4zdiobwl5uw2z27guxgu4dh/thumb3_g4zdiobwl5uw2z27guxgu4dh.jpg",
            "type": "picture"
          },
          {
            "link_to_media": "https://cdn2.aznude.com/g4zdiobwl5uw2z27gyxgu4dh/g4zdiobwl5uw2z27gyxgu4dh.jpg",
            "eid": null,
            "image_source": "https://cdn2.aznude.com/antibandit/g4zdiobwl5uw2z27gyxgu4dh/thumb3_g4zdiobwl5uw2z27gyxgu4dh.jpg",
            "type": "picture"
          }
        ]
      }
    ]
  },
  {
    "actress_name": "Anastasiya Mytrazhik",
    "birthplace": "Ukraine",
    "hashtag": "nude",
    "celeb_img_url": "https://cdn2.aznude.com/biopic/aznceleb-4016055_biopic.jpg",
    "view_count": "2.4K",
    "url": "https://aznude.com/view/celeb/a/anastasiyamytrazhik.html",
    "production_media_list": [
      {
        "type": "Movie",
        "title": "MOLODAYA GVARDIYA",
        "start_year": "2015",
        "end_year": null,
        "ongoing": false,
        "media_list": [
          {
            "link_to_media": "https://www.aznude.com/azncdn/dde4f03c19a64f3ea6cbcdeffba69aa7/dde4f03c19a64f3ea6cbcdeffba69aa7-hd.html",
            "eid": "https://www.aznude.com/embed/dde4f03c19a64f3ea6cbcdeffba69aa7-hd.html",
            "image_source": "https://cdn2.aznude.com/dde4f03c19a64f3ea6cbcdeffba69aa7/dde4f03c19a64f3ea6cbcdeffba69aa7-largeCelebPage-4.jpg",
            "type": "video"
          },
          {
            "link_to_media": "https://cdn2.aznude.com/2f788b9506d9428283de72bfaeb7d5df/2f788b9506d9428283de72bfaeb7d5df.jpg",
            "eid": null,
            "image_source": "https://cdn2.aznude.com/antibandit/2f788b9506d9428283de72bfaeb7d5df/thumb3_2f788b9506d9428283de72bfaeb7d5df.jpg",
            "type": "picture"
          },
          {
            "link_to_media": "https://cdn2.aznude.com/ef05cc56900f425c8ee6b392fb911caa/ef05cc56900f425c8ee6b392fb911caa.jpg",
            "eid": null,
            "image_source": "https://cdn2.aznude.com/antibandit/ef05cc56900f425c8ee6b392fb911caa/thumb3_ef05cc56900f425c8ee6b392fb911caa.jpg",
            "type": "picture"
          },
          {
            "link_to_media": "https://cdn2.aznude.com/b42b15af095046e1afab5fe2a7424ea9/b42b15af095046e1afab5fe2a7424ea9.jpg",
            "eid": null,
            "image_source": "https://cdn2.aznude.com/antibandit/b42b15af095046e1afab5fe2a7424ea9/thumb3_b42b15af095046e1afab5fe2a7424ea9.jpg",
            "type": "picture"
          }
        ]
      }
    ]
  },
  {
    "actress_name": "Rajia Baroudi",
    "birthplace": "Lebanon",
    "hashtag": "nude",
    "celeb_img_url": "https://cdn2.aznude.com/biopic/aznceleb-4016531_biopic.jpg",
    "view_count": "2.4K",
    "url": "https://aznude.com/view/celeb/r/rajiabaroudi.html",
    "production_media_list": [
      {
        "type": "Movie",
        "title": "STARSHIP: RISING",
        "start_year": "2014",
        "end_year": null,
        "ongoing": false,
        "media_list": [
          {
            "link_to_media": "https://www.aznude.com/azncdn/2ce50a84e79d4bf2a1accf3329f3a357/2ce50a84e79d4bf2a1accf3329f3a357-hd.html",
            "eid": "https://www.aznude.com/embed/2ce50a84e79d4bf2a1accf3329f3a357-hd.html",
            "image_source": "https://cdn2.aznude.com/2ce50a84e79d4bf2a1accf3329f3a357/2ce50a84e79d4bf2a1accf3329f3a357-largeCelebPage-4.jpg",
            "type": "video"
          },
          {
            "link_to_media": "https://cdn2.aznude.com/0c6ce43302cd4687a62b667004c4910e/0c6ce43302cd4687a62b667004c4910e.jpg",
            "eid": null,
            "image_source": "https://cdn2.aznude.com/antibandit/0c6ce43302cd4687a62b667004c4910e/thumb3_0c6ce43302cd4687a62b667004c4910e.jpg",
            "type": "picture"
          }
        ]
      }
    ]
  },
  {
    "actress_name": "Kathryn Kirkpatrick",
    "birthplace": "",
    "hashtag": "nude",
    "celeb_img_url": "https://cdn2.aznude.com/biopic/20750_biopic.jpg",
    "view_count": "2.4K",
    "url": "https://aznude.com/view/celeb/k/kathrynkirkpatrick.html",
    "production_media_list": [
      {
        "type": "Movie",
        "title": "PUNCH",
        "start_year": "2002",
        "end_year": null,
        "ongoing": false,
        "media_list": [
          {
            "link_to_media": "https://www.aznude.com/mrskin/kathrynkirkpatrick/punch/punch-kirkpat1-hi.html",
            "eid": "https://www.aznude.com/embed/punch-kirkpat1-hi.html",
            "image_source": "https://cdn2.aznude.com/kathrynkirkpatrick/punch/punch-kirkpat1-largeCelebPage-4.jpg",
            "type": "video"
          },
          {
            "link_to_media": "https://www.aznude.com/mrskin/kathrynkirkpatrick/punch/punch-kirkpat2-hi.html",
            "eid": "https://www.aznude.com/embed/punch-kirkpat2-hi.html",
            "image_source": "https://cdn2.aznude.com/kathrynkirkpatrick/punch/punch-kirkpat2-largeCelebPage-4.jpg",
            "type": "video"
          },
          {
            "link_to_media": "https://cdn1.aznude.com/kathrynkirkpatrick/punch/kirkpatrick-punch-n-6.jpg",
            "eid": null,
            "image_source": "https://cdn2.aznude.com/antibandit/kathrynkirkpatrick/punch/thumb3_kirkpatrick-punch-n-6.jpg",
            "type": "picture"
          },
          {
            "link_to_media": "https://cdn1.aznude.com/kathrynkirkpatrick/punch/kirkpatrick-punch-n-4.jpg",
            "eid": null,
            "image_source": "https://cdn2.aznude.com/antibandit/kathrynkirkpatrick/punch/thumb3_kirkpatrick-punch-n-4.jpg",
            "type": "picture"
          },
          {
            "link_to_media": "https://cdn1.aznude.com/kathrynkirkpatrick/punch/kirkpatrick-punch-n-8.jpg",
            "eid": null,
            "image_source": "https://cdn2.aznude.com/antibandit/kathrynkirkpatrick/punch/thumb3_kirkpatrick-punch-n-8.jpg",
            "type": "picture"
          },
          {
            "link_to_media": "https://cdn1.aznude.com/kathrynkirkpatrick/punch/kirkpatrick-punch-n-12.jpg",
            "eid": null,
            "image_source": "https://cdn2.aznude.com/antibandit/kathrynkirkpatrick/punch/thumb3_kirkpatrick-punch-n-12.jpg",
            "type": "picture"
          },
          {
            "link_to_media": "https://cdn1.aznude.com/kathrynkirkpatrick/punch/kirkpatrick-punch-n-10.jpg",
            "eid": null,
            "image_source": "https://cdn2.aznude.com/antibandit/kathrynkirkpatrick/punch/thumb3_kirkpatrick-punch-n-10.jpg",
            "type": "picture"
          },
          {
            "link_to_media": "https://cdn1.aznude.com/kathrynkirkpatrick/punch/kirkpatrick-punch-n-11.jpg",
            "eid": null,
            "image_source": "https://cdn2.aznude.com/antibandit/kathrynkirkpatrick/punch/thumb3_kirkpatrick-punch-n-11.jpg",
            "type": "picture"
          },
          {
            "link_to_media": "https://cdn1.aznude.com/kathrynkirkpatrick/punch/kirkpatrick-punch-n-2.jpg",
            "eid": null,
            "image_source": "https://cdn2.aznude.com/antibandit/kathrynkirkpatrick/punch/thumb3_kirkpatrick-punch-n-2.jpg",
            "type": "picture"
          },
          {
            "link_to_media": "https://cdn1.aznude.com/kathrynkirkpatrick/punch/kirkpatrick-punch-n-9.jpg",
            "eid": null,
            "image_source": "https://cdn2.aznude.com/antibandit/kathrynkirkpatrick/punch/thumb3_kirkpatrick-punch-n-9.jpg",
            "type": "picture"
          },
          {
            "link_to_media": "https://cdn1.aznude.com/kathrynkirkpatrick/punch/kirkpatrick-punch-n-3.jpg",
            "eid": null,
            "image_source": "https://cdn2.aznude.com/antibandit/kathrynkirkpatrick/punch/thumb3_kirkpatrick-punch-n-3.jpg",
            "type": "picture"
          },
          {
            "link_to_media": "https://cdn1.aznude.com/kathrynkirkpatrick/punch/kirkpatrick-punch-n-1.jpg",
            "eid": null,
            "image_source": "https://cdn2.aznude.com/antibandit/kathrynkirkpatrick/punch/thumb3_kirkpatrick-punch-n-1.jpg",
            "type": "picture"
          },
          {
            "link_to_media": "https://cdn1.aznude.com/kathrynkirkpatrick/punch/kirkpatrick-punch-n-7.jpg",
            "eid": null,
            "image_source": "https://cdn2.aznude.com/antibandit/kathrynkirkpatrick/punch/thumb3_kirkpatrick-punch-n-7.jpg",
            "type": "picture"
          },
          {
            "link_to_media": "https://cdn1.aznude.com/kathrynkirkpatrick/punch/kirkpatrick-punch-n-5.jpg",
            "eid": null,
            "image_source": "https://cdn2.aznude.com/antibandit/kathrynkirkpatrick/punch/thumb3_kirkpatrick-punch-n-5.jpg",
            "type": "picture"
          }
        ]
      }
    ]
  },
  {
    "actress_name": "Nancy Linehan Charles",
    "birthplace": "United States",
    "hashtag": "nude",
    "celeb_img_url": "https://cdn2.aznude.com/biopic/87421_biopic.jpg",
    "view_count": "2.4K",
    "url": "https://aznude.com/view/celeb/n/nancylinehancharles.html",
    "production_media_list": []
  },
  {
    "actress_name": "Meghan Leopard",
    "birthplace": "Canada",
    "hashtag": "nude",
    "celeb_img_url": "https://cdn2.aznude.com/biopic/aznceleb-4013714_biopic.jpg",
    "view_count": "2.4K",
    "url": "https://aznude.com/view/celeb/m/meghanleopard.html",
    "production_media_list": [
      {
        "type": "Movie",
        "title": "PLAYBOY PLUS",
        "start_year": "2009",
        "end_year": null,
        "ongoing": false,
        "media_list": [
          {
            "link_to_media": "https://www.aznude.com/azncdn/52249cf7ac8e426291d2ffe2573fb2f2/52249cf7ac8e426291d2ffe2573fb2f2-hd.html",
            "eid": "https://www.aznude.com/embed/52249cf7ac8e426291d2ffe2573fb2f2-hd.html",
            "image_source": "https://cdn2.aznude.com/52249cf7ac8e426291d2ffe2573fb2f2/52249cf7ac8e426291d2ffe2573fb2f2-largeCelebPage-4.jpg",
            "type": "video"
          },
          {
            "link_to_media": "https://www.aznude.com/azncdn/39d407904c1e493297a694272dfdaa88/39d407904c1e493297a694272dfdaa88-hd.html",
            "eid": "https://www.aznude.com/embed/39d407904c1e493297a694272dfdaa88-hd.html",
            "image_source": "https://cdn2.aznude.com/39d407904c1e493297a694272dfdaa88/39d407904c1e493297a694272dfdaa88-largeCelebPage-4.jpg",
            "type": "video"
          },
          {
            "link_to_media": "https://cdn2.aznude.com/a057fa33cd7e49d09a651bdbdffbfa09/a057fa33cd7e49d09a651bdbdffbfa09.jpg",
            "eid": null,
            "image_source": "https://cdn2.aznude.com/antibandit/a057fa33cd7e49d09a651bdbdffbfa09/thumb3_a057fa33cd7e49d09a651bdbdffbfa09.jpg",
            "type": "picture"
          },
          {
            "link_to_media": "https://cdn2.aznude.com/99c260a462f34745bcd48e825b92cccf/99c260a462f34745bcd48e825b92cccf.jpg",
            "eid": null,
            "image_source": "https://cdn2.aznude.com/antibandit/99c260a462f34745bcd48e825b92cccf/thumb3_99c260a462f34745bcd48e825b92cccf.jpg",
            "type": "picture"
          },
          {
            "link_to_media": "https://cdn2.aznude.com/3a4708a77f3040ec9510bd1452c43dfe/3a4708a77f3040ec9510bd1452c43dfe.jpg",
            "eid": null,
            "image_source": "https://cdn2.aznude.com/antibandit/3a4708a77f3040ec9510bd1452c43dfe/thumb3_3a4708a77f3040ec9510bd1452c43dfe.jpg",
            "type": "picture"
          },
          {
            "link_to_media": "https://cdn2.aznude.com/040596014c9c42bfb474f62afc6efdf6/040596014c9c42bfb474f62afc6efdf6.jpg",
            "eid": null,
            "image_source": "https://cdn2.aznude.com/antibandit/040596014c9c42bfb474f62afc6efdf6/thumb3_040596014c9c42bfb474f62afc6efdf6.jpg",
            "type": "picture"
          },
          {
            "link_to_media": "https://cdn2.aznude.com/4b4b8a5c9993407899cda3ef7d370e19/4b4b8a5c9993407899cda3ef7d370e19.jpg",
            "eid": null,
            "image_source": "https://cdn2.aznude.com/antibandit/4b4b8a5c9993407899cda3ef7d370e19/thumb3_4b4b8a5c9993407899cda3ef7d370e19.jpg",
            "type": "picture"
          },
          {
            "link_to_media": "https://cdn2.aznude.com/4d70a8993290424ea19343fb3995c677/4d70a8993290424ea19343fb3995c677.jpg",
            "eid": null,
            "image_source": "https://cdn2.aznude.com/antibandit/4d70a8993290424ea19343fb3995c677/thumb3_4d70a8993290424ea19343fb3995c677.jpg",
            "type": "picture"
          },
          {
            "link_to_media": "https://cdn2.aznude.com/ef6a318e02794636bf5feb4ec1bf46db/ef6a318e02794636bf5feb4ec1bf46db.jpg",
            "eid": null,
            "image_source": "https://cdn2.aznude.com/antibandit/ef6a318e02794636bf5feb4ec1bf46db/thumb3_ef6a318e02794636bf5feb4ec1bf46db.jpg",
            "type": "picture"
          }
        ]
      }
    ]
  },
  {
    "actress_name": "Gonny Gaakeer",
    "birthplace": "Netherlands",
    "hashtag": "nude",
    "celeb_img_url": "https://cdn2.aznude.com/biopic/gonny-gaakeer-0247ec08_biopic.jpg",
    "view_count": "2.4K",
    "url": "https://aznude.com/view/celeb/g/gonnygaakeer.html",
    "production_media_list": [
      {
        "type": "Series",
        "title": "ARES",
        "start_year": "2020",
        "end_year": null,
        "ongoing": true,
        "media_list": [
          {
            "link_to_media": "https://www.aznude.com/azncdn/gonnygaakeer/ares/ares-01x06-gaakeer-uhd-01_hd.html",
            "eid": "https://www.aznude.com/embed/ares-01x06-gaakeer-uhd-01_hd.html",
            "image_source": "https://cdn2.aznude.com/gonnygaakeer/ares/Ares-01x06-Gaakeer-UHD-01_largeCelebPage-4.jpg",
            "type": "video"
          },
          {
            "link_to_media": "https://cdn2.aznude.com/gonnygaakeer/ares/gonny_gaakeer_604f64.jpg",
            "eid": null,
            "image_source": "https://cdn2.aznude.com/antibandit/gonnygaakeer/ares/thumb3_gonny_gaakeer_604f64.jpg",
            "type": "picture"
          },
          {
            "link_to_media": "https://cdn2.aznude.com/gonnygaakeer/ares/gonny_gaakeer_329037.jpg",
            "eid": null,
            "image_source": "https://cdn2.aznude.com/antibandit/gonnygaakeer/ares/thumb3_gonny_gaakeer_329037.jpg",
            "type": "picture"
          },
          {
            "link_to_media": "https://cdn2.aznude.com/gonnygaakeer/ares/gonny_gaakeer_13462a.jpg",
            "eid": null,
            "image_source": "https://cdn2.aznude.com/antibandit/gonnygaakeer/ares/thumb3_gonny_gaakeer_13462a.jpg",
            "type": "picture"
          }
        ]
      }
    ]
  },
  {
    "actress_name": "Xochitl Nunez",
    "birthplace": "Mexico",
    "hashtag": "nude",
    "celeb_img_url": "https://cdn2.aznude.com/biopic/aznceleb-4010541_biopic.jpg",
    "view_count": "2.4K",
    "url": "https://aznude.com/view/celeb/x/xochitlnunez.html",
    "production_media_list": [
      {
        "type": "Movie",
        "title": "LA SUEGRA DE TODOS",
        "start_year": "2016",
        "end_year": null,
        "ongoing": false,
        "media_list": [
          {
            "link_to_media": "https://www.aznude.com/azncdn/c6ef2d7d34e3414abf13cbf38aa50890/c6ef2d7d34e3414abf13cbf38aa50890-hi.html",
            "eid": "https://www.aznude.com/embed/c6ef2d7d34e3414abf13cbf38aa50890-hi.html",
            "image_source": "https://cdn2.aznude.com/c6ef2d7d34e3414abf13cbf38aa50890/c6ef2d7d34e3414abf13cbf38aa50890-largeCelebPage-4.jpg",
            "type": "video"
          },
          {
            "link_to_media": "https://www.aznude.com/azncdn/83f7ed5ee9a844c58d27a39ae2cc5dee/83f7ed5ee9a844c58d27a39ae2cc5dee-hi.html",
            "eid": "https://www.aznude.com/embed/83f7ed5ee9a844c58d27a39ae2cc5dee-hi.html",
            "image_source": "https://cdn2.aznude.com/83f7ed5ee9a844c58d27a39ae2cc5dee/83f7ed5ee9a844c58d27a39ae2cc5dee-largeCelebPage-4.jpg",
            "type": "video"
          },
          {
            "link_to_media": "https://cdn2.aznude.com/b136369079b8463ebadf9963a4505393/b136369079b8463ebadf9963a4505393.jpg",
            "eid": null,
            "image_source": "https://cdn2.aznude.com/antibandit/b136369079b8463ebadf9963a4505393/thumb3_b136369079b8463ebadf9963a4505393.jpg",
            "type": "picture"
          },
          {
            "link_to_media": "https://cdn2.aznude.com/ce5f5fbfee8f43679a217f2b46fc975a/ce5f5fbfee8f43679a217f2b46fc975a.jpg",
            "eid": null,
            "image_source": "https://cdn2.aznude.com/antibandit/ce5f5fbfee8f43679a217f2b46fc975a/thumb3_ce5f5fbfee8f43679a217f2b46fc975a.jpg",
            "type": "picture"
          },
          {
            "link_to_media": "https://cdn2.aznude.com/329c87e4f404462d9d9dde85c57c490d/329c87e4f404462d9d9dde85c57c490d.jpg",
            "eid": null,
            "image_source": "https://cdn2.aznude.com/antibandit/329c87e4f404462d9d9dde85c57c490d/thumb3_329c87e4f404462d9d9dde85c57c490d.jpg",
            "type": "picture"
          },
          {
            "link_to_media": "https://cdn2.aznude.com/e9b03ce81cb243168a053b6054b3cb5e/e9b03ce81cb243168a053b6054b3cb5e.jpg",
            "eid": null,
            "image_source": "https://cdn2.aznude.com/antibandit/e9b03ce81cb243168a053b6054b3cb5e/thumb3_e9b03ce81cb243168a053b6054b3cb5e.jpg",
            "type": "picture"
          },
          {
            "link_to_media": "https://cdn2.aznude.com/c4318f016d3c4664ac44b972ea69d73d/c4318f016d3c4664ac44b972ea69d73d.jpg",
            "eid": null,
            "image_source": "https://cdn2.aznude.com/antibandit/c4318f016d3c4664ac44b972ea69d73d/thumb3_c4318f016d3c4664ac44b972ea69d73d.jpg",
            "type": "picture"
          },
          {
            "link_to_media": "https://cdn2.aznude.com/04580e3c00254902806a864118503808/04580e3c00254902806a864118503808.jpg",
            "eid": null,
            "image_source": "https://cdn2.aznude.com/antibandit/04580e3c00254902806a864118503808/thumb3_04580e3c00254902806a864118503808.jpg",
            "type": "picture"
          },
          {
            "link_to_media": "https://cdn2.aznude.com/262dcc98b5324cccab9d1350f0833ff7/262dcc98b5324cccab9d1350f0833ff7.jpg",
            "eid": null,
            "image_source": "https://cdn2.aznude.com/antibandit/262dcc98b5324cccab9d1350f0833ff7/thumb3_262dcc98b5324cccab9d1350f0833ff7.jpg",
            "type": "picture"
          }
        ]
      }
    ]
  },
  {
    "actress_name": "Arabella Durkin",
    "birthplace": "United Kingdom",
    "hashtag": "nude",
    "celeb_img_url": "https://cdn2.aznude.com/biopic/aznceleb-4011513_biopic.jpg",
    "view_count": "2.4K",
    "url": "https://aznude.com/view/celeb/a/arabelladurkin.html",
    "production_media_list": [
      {
        "type": "Series",
        "title": "PLANNERS",
        "start_year": "2023",
        "end_year": null,
        "ongoing": false,
        "media_list": [
          {
            "link_to_media": "https://cdn2.aznude.com/9b0c60ec8ad74403ad2826a2db63eb20/9b0c60ec8ad74403ad2826a2db63eb20.jpg",
            "eid": null,
            "image_source": "https://cdn2.aznude.com/antibandit/9b0c60ec8ad74403ad2826a2db63eb20/thumb3_9b0c60ec8ad74403ad2826a2db63eb20.jpg",
            "type": "picture"
          },
          {
            "link_to_media": "https://cdn2.aznude.com/466080470b7141a4b29f93a593b52cd4/466080470b7141a4b29f93a593b52cd4.jpg",
            "eid": null,
            "image_source": "https://cdn2.aznude.com/antibandit/466080470b7141a4b29f93a593b52cd4/thumb3_466080470b7141a4b29f93a593b52cd4.jpg",
            "type": "picture"
          },
          {
            "link_to_media": "https://cdn2.aznude.com/31d031c31b4d480ca414a192e23b4cd1/31d031c31b4d480ca414a192e23b4cd1.jpg",
            "eid": null,
            "image_source": "https://cdn2.aznude.com/antibandit/31d031c31b4d480ca414a192e23b4cd1/thumb3_31d031c31b4d480ca414a192e23b4cd1.jpg",
            "type": "picture"
          },
          {
            "link_to_media": "https://cdn2.aznude.com/88bb9a22373e4f5c80529e1f8913d3fb/88bb9a22373e4f5c80529e1f8913d3fb.jpg",
            "eid": null,
            "image_source": "https://cdn2.aznude.com/antibandit/88bb9a22373e4f5c80529e1f8913d3fb/thumb3_88bb9a22373e4f5c80529e1f8913d3fb.jpg",
            "type": "picture"
          },
          {
            "link_to_media": "https://cdn2.aznude.com/c4cd676638f5426785fa84a13065876c/c4cd676638f5426785fa84a13065876c.jpg",
            "eid": null,
            "image_source": "https://cdn2.aznude.com/antibandit/c4cd676638f5426785fa84a13065876c/thumb3_c4cd676638f5426785fa84a13065876c.jpg",
            "type": "picture"
          }
        ]
      },
      {
        "type": "Story",
        "title": "ARABELLA DURKIN TOPLESS FOR ZOO MAGAZINE",
        "start_year": "2014",
        "end_year": null,
        "ongoing": false,
        "media_list": [
          {
            "link_to_media": "https://www.aznude.com/azncdn/bca4992fae2144fd8ad51135b506cd76/bca4992fae2144fd8ad51135b506cd76-hd.html",
            "eid": "https://www.aznude.com/embed/bca4992fae2144fd8ad51135b506cd76-hd.html",
            "image_source": "https://cdn2.aznude.com/bca4992fae2144fd8ad51135b506cd76/bca4992fae2144fd8ad51135b506cd76-largeCelebPage-4.jpg",
            "type": "video"
          }
        ]
      }
    ]
  },
  {
    "actress_name": "Monika Krzywkowska",
    "birthplace": "Poland",
    "hashtag": "nude",
    "celeb_img_url": "https://cdn2.aznude.com/biopic/aznceleb-4015106_biopic.jpg",
    "view_count": "2.4K",
    "url": "https://aznude.com/view/celeb/m/monikakrzywkowska.html",
    "production_media_list": [
      {
        "type": "Series",
        "title": "POLOWANIE NA CMY",
        "start_year": "2023",
        "end_year": null,
        "ongoing": false,
        "media_list": [
          {
            "link_to_media": "https://www.aznude.com/azncdn/112524a6c21449cf8a2b3268652c0173/112524a6c21449cf8a2b3268652c0173-hd.html",
            "eid": "https://www.aznude.com/embed/112524a6c21449cf8a2b3268652c0173-hd.html",
            "image_source": "https://cdn2.aznude.com/112524a6c21449cf8a2b3268652c0173/112524a6c21449cf8a2b3268652c0173-largeCelebPage-4.jpg",
            "type": "video"
          },
          {
            "link_to_media": "https://cdn2.aznude.com/70ec3232ad6e4573816a5f3323de43ec/70ec3232ad6e4573816a5f3323de43ec.jpg",
            "eid": null,
            "image_source": "https://cdn2.aznude.com/antibandit/70ec3232ad6e4573816a5f3323de43ec/thumb3_70ec3232ad6e4573816a5f3323de43ec.jpg",
            "type": "picture"
          },
          {
            "link_to_media": "https://cdn2.aznude.com/c0270bee0e42402da53662f1fb1c8e3a/c0270bee0e42402da53662f1fb1c8e3a.jpg",
            "eid": null,
            "image_source": "https://cdn2.aznude.com/antibandit/c0270bee0e42402da53662f1fb1c8e3a/thumb3_c0270bee0e42402da53662f1fb1c8e3a.jpg",
            "type": "picture"
          },
          {
            "link_to_media": "https://cdn2.aznude.com/9df518e4995943da8972d7ef550dc40c/9df518e4995943da8972d7ef550dc40c.jpg",
            "eid": null,
            "image_source": "https://cdn2.aznude.com/antibandit/9df518e4995943da8972d7ef550dc40c/thumb3_9df518e4995943da8972d7ef550dc40c.jpg",
            "type": "picture"
          },
          {
            "link_to_media": "https://cdn2.aznude.com/577161f823804d8f9b0782bc04ac72b3/577161f823804d8f9b0782bc04ac72b3.jpg",
            "eid": null,
            "image_source": "https://cdn2.aznude.com/antibandit/577161f823804d8f9b0782bc04ac72b3/thumb3_577161f823804d8f9b0782bc04ac72b3.jpg",
            "type": "picture"
          }
        ]
      },
      {
        "type": "Movie",
        "title": "SAMO ZYCIE",
        "start_year": "2002",
        "end_year": null,
        "ongoing": false,
        "media_list": [
          {
            "link_to_media": "https://www.aznude.com/azncdn/058f899f3f0f4500a4bbcba1bd90bdd9/058f899f3f0f4500a4bbcba1bd90bdd9-hi.html",
            "eid": "https://www.aznude.com/embed/058f899f3f0f4500a4bbcba1bd90bdd9-hi.html",
            "image_source": "https://cdn2.aznude.com/058f899f3f0f4500a4bbcba1bd90bdd9/058f899f3f0f4500a4bbcba1bd90bdd9-largeCelebPage-4.jpg",
            "type": "video"
          },
          {
            "link_to_media": "https://cdn2.aznude.com/6533efd513ef45048f9694b04f18000f/6533efd513ef45048f9694b04f18000f.jpg",
            "eid": null,
            "image_source": "https://cdn2.aznude.com/antibandit/6533efd513ef45048f9694b04f18000f/thumb3_6533efd513ef45048f9694b04f18000f.jpg",
            "type": "picture"
          },
          {
            "link_to_media": "https://cdn2.aznude.com/7d08f3cf7d2e4ce1b47125285eb79157/7d08f3cf7d2e4ce1b47125285eb79157.jpg",
            "eid": null,
            "image_source": "https://cdn2.aznude.com/antibandit/7d08f3cf7d2e4ce1b47125285eb79157/thumb3_7d08f3cf7d2e4ce1b47125285eb79157.jpg",
            "type": "picture"
          },
          {
            "link_to_media": "https://cdn2.aznude.com/d4d44c006dd2481ebc0e37f59e523f1a/d4d44c006dd2481ebc0e37f59e523f1a.jpg",
            "eid": null,
            "image_source": "https://cdn2.aznude.com/antibandit/d4d44c006dd2481ebc0e37f59e523f1a/thumb3_d4d44c006dd2481ebc0e37f59e523f1a.jpg",
            "type": "picture"
          },
          {
            "link_to_media": "https://cdn2.aznude.com/850c9ff8f1224d5a8dec50c20978d4b1/850c9ff8f1224d5a8dec50c20978d4b1.jpg",
            "eid": null,
            "image_source": "https://cdn2.aznude.com/antibandit/850c9ff8f1224d5a8dec50c20978d4b1/thumb3_850c9ff8f1224d5a8dec50c20978d4b1.jpg",
            "type": "picture"
          }
        ]
      }
    ]
  },
  {
    "actress_name": "Yailene Sierra",
    "birthplace": "Cuba",
    "hashtag": "nude",
    "celeb_img_url": "https://cdn2.aznude.com/biopic/60222_biopic.jpg",
    "view_count": "2.4K",
    "url": "https://aznude.com/view/celeb/y/yailenesierra.html",
    "production_media_list": [
      {
        "type": "Movie",
        "title": "HABANA BLUES",
        "start_year": "2005",
        "end_year": null,
        "ongoing": false,
        "media_list": [
          {
            "link_to_media": "https://cdn2.aznude.com/a9092c53086948a2a53a2c9bdcc32db0/a9092c53086948a2a53a2c9bdcc32db0.jpg",
            "eid": null,
            "image_source": "https://cdn2.aznude.com/antibandit/a9092c53086948a2a53a2c9bdcc32db0/thumb3_a9092c53086948a2a53a2c9bdcc32db0.jpg",
            "type": "picture"
          }
        ]
      },
      {
        "type": "Series",
        "title": "EL SINDROME DE ULISES",
        "start_year": null,
        "end_year": null,
        "ongoing": false,
        "media_list": [
          {
            "link_to_media": "https://www.aznude.com/azncdn/f84b517dee5640bb819d2e12a7122142/f84b517dee5640bb819d2e12a7122142-hd.html",
            "eid": "https://www.aznude.com/embed/f84b517dee5640bb819d2e12a7122142-hd.html",
            "image_source": "https://cdn2.aznude.com/f84b517dee5640bb819d2e12a7122142/f84b517dee5640bb819d2e12a7122142-largeCelebPage-4.jpg",
            "type": "video"
          },
          {
            "link_to_media": "https://cdn2.aznude.com/1de4830dcb1b4653af69cfab6f3c0a51/1de4830dcb1b4653af69cfab6f3c0a51.jpg",
            "eid": null,
            "image_source": "https://cdn2.aznude.com/antibandit/1de4830dcb1b4653af69cfab6f3c0a51/thumb3_1de4830dcb1b4653af69cfab6f3c0a51.jpg",
            "type": "picture"
          }
        ]
      }
    ]
  },
  {
    "actress_name": "Tara Thompson",
    "birthplace": "United States",
    "hashtag": "nude",
    "celeb_img_url": "https://cdn2.aznude.com/biopic/34467_biopic.jpg",
    "view_count": "2.4K",
    "url": "https://aznude.com/view/celeb/t/tarathompson.html",
    "production_media_list": [
      {
        "type": "Series",
        "title": "THE MOUNTAIN",
        "start_year": "2004",
        "end_year": null,
        "ongoing": false,
        "media_list": []
      }
    ]
  },
  {
    "actress_name": "Katharine Emmer",
    "birthplace": "",
    "hashtag": "nude",
    "celeb_img_url": "https://cdn2.aznude.com/biopic/katharine-emmer-e4a50dd3_biopic.jpg",
    "view_count": "2.4K",
    "url": "https://aznude.com/view/celeb/k/katharineemmer.html",
    "production_media_list": [
      {
        "type": "Movie",
        "title": "LIFE IN COLOR",
        "start_year": null,
        "end_year": null,
        "ongoing": false,
        "media_list": []
      }
    ]
  }
]
