[{"actress_name": "Beatrice Peters", "birthplace": "Germany", "hashtag": "nude", "celeb_img_url": "https://cdn2.aznude.com/biopic/aznceleb-4507483_biopic.jpg", "view_count": "778", "url": "https://aznude.com/view/celeb/b/beatricepeters.html", "production_media_list": [{"type": "Story", "title": "BEATRICE PETERS SEXY PHOTOS COLLECTION", "start_year": "2022", "end_year": null, "ongoing": false, "media_list": []}]}, {"actress_name": "Melissa Diarra", "birthplace": "France", "hashtag": "nude", "celeb_img_url": "https://cdn2.aznude.com/biopic/aznceleb-4011596_biopic.jpg", "view_count": "778", "url": "https://aznude.com/view/celeb/m/melissadiarra.html", "production_media_list": [{"type": "Series", "title": "PANDORE", "start_year": "2022", "end_year": null, "ongoing": false, "media_list": [{"link_to_media": "/azncdn/365dca676b85410c9096fd4aa4a902b5/365dca676b85410c9096fd4aa4a902b5-hd.html", "eid": "/embed/365dca676b85410c9096fd4aa4a902b5-hd.html", "image_source": "//cdn2.aznude.com/365dca676b85410c9096fd4aa4a902b5/365dca676b85410c9096fd4aa4a902b5-largeCelebPage-4.jpg", "type": "video"}, {"link_to_media": "/azncdn/2db8aec9ded741b599394774b5da7f16/2db8aec9ded741b599394774b5da7f16-hd.html", "eid": "/embed/2db8aec9ded741b599394774b5da7f16-hd.html", "image_source": "//cdn2.aznude.com/2db8aec9ded741b599394774b5da7f16/2db8aec9ded741b599394774b5da7f16-largeCelebPage-4.jpg", "type": "video"}, {"link_to_media": "https://cdn2.aznude.com/1d8aa85cdf06479083a3983c674adc2d/1d8aa85cdf06479083a3983c674adc2d.jpg", "eid": null, "image_source": "https://cdn2.aznude.com/antibandit/1d8aa85cdf06479083a3983c674adc2d/thumb3_1d8aa85cdf06479083a3983c674adc2d.jpg", "type": "picture"}, {"link_to_media": "https://cdn2.aznude.com/5a1567bebb8b4c83851d95d1ea78d9b6/5a1567bebb8b4c83851d95d1ea78d9b6.jpg", "eid": null, "image_source": "https://cdn2.aznude.com/antibandit/5a1567bebb8b4c83851d95d1ea78d9b6/thumb3_5a1567bebb8b4c83851d95d1ea78d9b6.jpg", "type": "picture"}, {"link_to_media": "https://cdn2.aznude.com/be09d4b4b4db47f1949c1ca7905e9cc9/be09d4b4b4db47f1949c1ca7905e9cc9.jpg", "eid": null, "image_source": "https://cdn2.aznude.com/antibandit/be09d4b4b4db47f1949c1ca7905e9cc9/thumb3_be09d4b4b4db47f1949c1ca7905e9cc9.jpg", "type": "picture"}, {"link_to_media": "https://cdn2.aznude.com/40ccb8c86a8142ff8e142fbb5cd899ac/40ccb8c86a8142ff8e142fbb5cd899ac.jpg", "eid": null, "image_source": "https://cdn2.aznude.com/antibandit/40ccb8c86a8142ff8e142fbb5cd899ac/thumb3_40ccb8c86a8142ff8e142fbb5cd899ac.jpg", "type": "picture"}, {"link_to_media": "https://cdn2.aznude.com/06d07fea716c46028cdfacd6339fec8f/06d07fea716c46028cdfacd6339fec8f.jpg", "eid": null, "image_source": "https://cdn2.aznude.com/antibandit/06d07fea716c46028cdfacd6339fec8f/thumb3_06d07fea716c46028cdfacd6339fec8f.jpg", "type": "picture"}, {"link_to_media": "https://cdn2.aznude.com/2755016c06df40cdbd50ef912c1c7342/2755016c06df40cdbd50ef912c1c7342.jpg", "eid": null, "image_source": "https://cdn2.aznude.com/antibandit/2755016c06df40cdbd50ef912c1c7342/thumb3_2755016c06df40cdbd50ef912c1c7342.jpg", "type": "picture"}]}]}, {"actress_name": "Eva Gelb", "birthplace": "", "hashtag": "nude", "celeb_img_url": "https://cdn2.aznude.com/biopic/actress_biopic_default-a7bcb7dd5a7afc9ad5e7415750030973.png", "view_count": "776", "url": "https://aznude.com/view/celeb/e/evagelb.html", "production_media_list": [{"type": "Movie", "title": "LIEB VATERLAND MAGST RUHIG SEIN", "start_year": "1976", "end_year": null, "ongoing": false, "media_list": []}]}, {"actress_name": "Christina Luft", "birthplace": "", "hashtag": "nude", "celeb_img_url": "https://cdn2.aznude.com/biopic/aznceleb-4500058_biopic.jpg", "view_count": "776", "url": "https://aznude.com/view/celeb/c/christinaluft.html", "production_media_list": [{"type": "Story", "title": "CHRISTINA LUFT SEXY SOCIAL MEDIA PHOTOS COLLECTION", "start_year": "2022", "end_year": null, "ongoing": false, "media_list": []}, {"type": "Story", "title": "CHRISTINA LUFT SEXY COLLECTION SOCIAL MEDIA SHOWING THE DANCER", "start_year": "2022", "end_year": null, "ongoing": false, "media_list": []}, {"type": "Story", "title": "CHRISTINA LUFT SEXY BIKINI PHOTOS COLLECTION", "start_year": "2022", "end_year": null, "ongoing": false, "media_list": []}, {"type": "Story", "title": "CHRISTINA LUFT SEXY AND HOT PHOTOS COLLECTION", "start_year": "2022", "end_year": null, "ongoing": false, "media_list": []}, {"type": "Story", "title": "CHRISTINA LUFT SEXY PHOTOS COLLECTION", "start_year": "2021", "end_year": null, "ongoing": false, "media_list": []}]}, {"actress_name": "Maya Rae", "birthplace": "", "hashtag": "nude", "celeb_img_url": "https://cdn2.aznude.com/biopic/aznceleb-4500117_biopic.jpg", "view_count": "776", "url": "https://aznude.com/view/celeb/m/mayarae.html", "production_media_list": [{"type": "Story", "title": "MAYA RAE SEXY POSES NAKED SHOWING OFF HER TITS AND PUSSY IN A PLAYBOY PHOTOSHOOT", "start_year": "2017", "end_year": null, "ongoing": false, "media_list": []}]}, {"actress_name": "Kendall Marie", "birthplace": "", "hashtag": "nude", "celeb_img_url": "https://cdn2.aznude.com/biopic/story_celeb_1534710703-1347623690.jpg", "view_count": "776", "url": "https://aznude.com/view/celeb/k/kendallmarie.html", "production_media_list": [{"type": "Story", "title": "KENDALL MARIE NUDE AND SEXY IN PHOTOSHOOT BY ANGEL ALFARO", "start_year": "2018", "end_year": null, "ongoing": false, "media_list": []}]}, {"actress_name": "Nicole Spiller", "birthplace": "", "hashtag": "nude", "celeb_img_url": "https://cdn2.aznude.com/biopic/story_celeb_1556457389-1143122737.jpg", "view_count": "776", "url": "https://aznude.com/view/celeb/n/nicolespiller.html", "production_media_list": [{"type": "Story", "title": "NICOLE SPILLER SEXY NON-NUDE HOT PHOTOS FROM INSTAGRAM", "start_year": "2019", "end_year": null, "ongoing": false, "media_list": []}, {"type": "Story", "title": "NICOLE SPILLER NUDE AND SEXUAL 2017 PHOTOS", "start_year": "2017", "end_year": null, "ongoing": false, "media_list": []}]}, {"actress_name": "Veronica Hidalgo", "birthplace": "", "hashtag": "nude", "celeb_img_url": "https://cdn2.aznude.com/biopic/story_celeb_1566671305-557341974.jpg", "view_count": "776", "url": "https://aznude.com/view/celeb/v/veronicahidalgo.html", "production_media_list": [{"type": "Story", "title": "VERONICA HIDALGO SEEN IN A BIKINI WHILE SHOOTING IN COSTA BRAVA", "start_year": "2020", "end_year": null, "ongoing": false, "media_list": []}, {"type": "Story", "title": "VERONICA HIDALGO MAKES A SPLASH WHILE ON VACATION IN COSTA BRAVA, BARCELONA, SPAIN", "start_year": "2019", "end_year": null, "ongoing": false, "media_list": []}]}, {"actress_name": "Polina Knyazeva", "birthplace": "", "hashtag": "nude", "celeb_img_url": "https://cdn2.aznude.com/biopic/story_celeb_1592433634-1530630885.jpg", "view_count": "776", "url": "https://aznude.com/view/celeb/p/polinaknyazeva.html", "production_media_list": [{"type": "Story", "title": "POLINA KNYAZEVA DISPLAYS HER NAKED SLIM BODY IN A PHOTOSHOOT BY ALEXEY TRIFONOV", "start_year": "2017", "end_year": null, "ongoing": false, "media_list": []}]}, {"actress_name": "Annabel Barrett", "birthplace": "United States", "hashtag": "nude", "celeb_img_url": "https://cdn2.aznude.com/biopic/annabel-barrett-fb2b5552_biopic.jpg", "view_count": "776", "url": "https://aznude.com/view/celeb/a/annabelbarrett.html", "production_media_list": [{"type": "Movie", "title": "THIS GAMES CALLED MURDER", "start_year": "2021", "end_year": null, "ongoing": false, "media_list": [{"link_to_media": "/azncdn/annabelbarrett/thisgamescalledmurder/thisgamescalledmurder-barrett-uhd-03-hd.html", "eid": "/embed/thisgamescalledmurder-barrett-uhd-03-hd.html", "image_source": "//cdn2.aznude.com/annabelbarrett/thisgamescalledmurder/ThisGamesCalledMurder-Barrett-UHD-03-largeCelebPage-4.jpg", "type": "video"}, {"link_to_media": "/azncdn/annabelbarrett/thisgamescalledmurder/thisgamescalledmurder-barrett-uhd-02_hd.html", "eid": "/embed/thisgamescalledmurder-barrett-uhd-02_hd.html", "image_source": "//cdn2.aznude.com/annabelbarrett/thisgamescalledmurder/ThisGamesCalledMurder-Barrett-UHD-02_largeCelebPage-4.jpg", "type": "video"}, {"link_to_media": "/azncdn/annabelbarrett/thisgamescalledmurder/thisgamescalledmurder-barrett-uhd-01-hd.html", "eid": "/embed/thisgamescalledmurder-barrett-uhd-01-hd.html", "image_source": "//cdn2.aznude.com/annabelbarrett/thisgamescalledmurder/ThisGamesCalledMurder-Barrett-UHD-01-largeCelebPage-4.jpg", "type": "video"}, {"link_to_media": "https://cdn2.aznude.com/annabelbarrett/thisgamescalledmurder/annabel_barrett_a63989.jpg", "eid": null, "image_source": "https://cdn2.aznude.com/antibandit/annabelbarrett/thisgamescalledmurder/thumb3_annabel_barrett_a63989.jpg", "type": "picture"}, {"link_to_media": "https://cdn2.aznude.com/annabelbarrett/thisgamescalledmurder/annabel_barrett_884e41.jpg", "eid": null, "image_source": "https://cdn2.aznude.com/antibandit/annabelbarrett/thisgamescalledmurder/thumb3_annabel_barrett_884e41.jpg", "type": "picture"}, {"link_to_media": "https://cdn2.aznude.com/annabelbarrett/thisgamescalledmurder/annabel_barrett_a57786.jpg", "eid": null, "image_source": "https://cdn2.aznude.com/antibandit/annabelbarrett/thisgamescalledmurder/thumb3_annabel_barrett_a57786.jpg", "type": "picture"}, {"link_to_media": "https://cdn2.aznude.com/annabelbarrett/thisgamescalledmurder/annabel_barrett_5ff08b.jpg", "eid": null, "image_source": "https://cdn2.aznude.com/antibandit/annabelbarrett/thisgamescalledmurder/thumb3_annabel_barrett_5ff08b.jpg", "type": "picture"}, {"link_to_media": "https://cdn2.aznude.com/annabelbarrett/thisgamescalledmurder/annabel_barrett_544c96.jpg", "eid": null, "image_source": "https://cdn2.aznude.com/antibandit/annabelbarrett/thisgamescalledmurder/thumb3_annabel_barrett_544c96.jpg", "type": "picture"}]}]}, {"actress_name": "Dorota Krempa", "birthplace": "Poland", "hashtag": "nude", "celeb_img_url": "https://cdn2.aznude.com/biopic/aznceleb-4003363_biopic.jpg", "view_count": "776", "url": "https://aznude.com/view/celeb/d/dorotakrempa.html", "production_media_list": [{"type": "Movie", "title": "NA WSPOLNEJ", "start_year": "2003", "end_year": null, "ongoing": false, "media_list": [{"link_to_media": "/azncdn/192d4f7c30344d0f882f292a8e7e0eb4/192d4f7c30344d0f882f292a8e7e0eb4-hd.html", "eid": "/embed/192d4f7c30344d0f882f292a8e7e0eb4-hd.html", "image_source": "//cdn2.aznude.com/192d4f7c30344d0f882f292a8e7e0eb4/192d4f7c30344d0f882f292a8e7e0eb4-largeCelebPage-4.jpg", "type": "video"}, {"link_to_media": "/azncdn/14269667ef02432ca800f41669924667/14269667ef02432ca800f41669924667-hd.html", "eid": "/embed/14269667ef02432ca800f41669924667-hd.html", "image_source": "//cdn2.aznude.com/14269667ef02432ca800f41669924667/14269667ef02432ca800f41669924667-largeCelebPage-4.jpg", "type": "video"}, {"link_to_media": "https://cdn2.aznude.com/4c51c26d7a9b4225bae3a1e1d27b209c/4c51c26d7a9b4225bae3a1e1d27b209c.jpg", "eid": null, "image_source": "https://cdn2.aznude.com/antibandit/4c51c26d7a9b4225bae3a1e1d27b209c/thumb3_4c51c26d7a9b4225bae3a1e1d27b209c.jpg", "type": "picture"}, {"link_to_media": "https://cdn2.aznude.com/eb8f6f4a3e934860a96748197bb8d315/eb8f6f4a3e934860a96748197bb8d315.jpg", "eid": null, "image_source": "https://cdn2.aznude.com/antibandit/eb8f6f4a3e934860a96748197bb8d315/thumb3_eb8f6f4a3e934860a96748197bb8d315.jpg", "type": "picture"}, {"link_to_media": "https://cdn2.aznude.com/fbe3cd4b0a4640beade4240dc732cbc3/fbe3cd4b0a4640beade4240dc732cbc3.jpg", "eid": null, "image_source": "https://cdn2.aznude.com/antibandit/fbe3cd4b0a4640beade4240dc732cbc3/thumb3_fbe3cd4b0a4640beade4240dc732cbc3.jpg", "type": "picture"}, {"link_to_media": "https://cdn2.aznude.com/68906dca380f40f2ba5166cca7238ee6/68906dca380f40f2ba5166cca7238ee6.jpg", "eid": null, "image_source": "https://cdn2.aznude.com/antibandit/68906dca380f40f2ba5166cca7238ee6/thumb3_68906dca380f40f2ba5166cca7238ee6.jpg", "type": "picture"}, {"link_to_media": "https://cdn2.aznude.com/7a9318ace0c5465497d701627f85a0f7/7a9318ace0c5465497d701627f85a0f7.jpg", "eid": null, "image_source": "https://cdn2.aznude.com/antibandit/7a9318ace0c5465497d701627f85a0f7/thumb3_7a9318ace0c5465497d701627f85a0f7.jpg", "type": "picture"}, {"link_to_media": "https://cdn2.aznude.com/8429f004569f4b2390f8df57e304af2d/8429f004569f4b2390f8df57e304af2d.jpg", "eid": null, "image_source": "https://cdn2.aznude.com/antibandit/8429f004569f4b2390f8df57e304af2d/thumb3_8429f004569f4b2390f8df57e304af2d.jpg", "type": "picture"}, {"link_to_media": "https://cdn2.aznude.com/bf0b06ee0762403897cdd88e38c5a687/bf0b06ee0762403897cdd88e38c5a687.jpg", "eid": null, "image_source": "https://cdn2.aznude.com/antibandit/bf0b06ee0762403897cdd88e38c5a687/thumb3_bf0b06ee0762403897cdd88e38c5a687.jpg", "type": "picture"}, {"link_to_media": "https://cdn2.aznude.com/de14ba9a8a6747f98a5892415dd2944f/de14ba9a8a6747f98a5892415dd2944f.jpg", "eid": null, "image_source": "https://cdn2.aznude.com/antibandit/de14ba9a8a6747f98a5892415dd2944f/thumb3_de14ba9a8a6747f98a5892415dd2944f.jpg", "type": "picture"}, {"link_to_media": "https://cdn2.aznude.com/de57180b885e4c258709c49caecabd64/de57180b885e4c258709c49caecabd64.jpg", "eid": null, "image_source": "https://cdn2.aznude.com/antibandit/de57180b885e4c258709c49caecabd64/thumb3_de57180b885e4c258709c49caecabd64.jpg", "type": "picture"}]}]}, {"actress_name": "CG", "birthplace": "", "hashtag": "nude", "celeb_img_url": "https://cdn2.aznude.com/biopic/cg-d121ffbb_biopic.jpg", "view_count": "776", "url": "https://aznude.com/view/celeb/c/cg.html", "production_media_list": [{"type": "Series", "title": "QUEER AS FOLK", "start_year": "2022", "end_year": null, "ongoing": true, "media_list": [{"link_to_media": "/azncdn/cg/queerasfolk/queerasfolk-01x07-cattrall-cg-hd-01_hd.html", "eid": "/embed/queerasfolk-01x07-cattrall-cg-hd-01_hd.html", "image_source": "//cdn2.aznude.com/cg/queerasfolk/QueerAsFolk-01x07-Cattrall-CG-HD-01_largeCelebPage-4.jpg", "type": "video"}, {"link_to_media": "/azncdn/cg/queerasfolk/queerasfolk01x02-cgkeitel-hd-01_hd.html", "eid": "/embed/queerasfolk01x02-cgkeitel-hd-01_hd.html", "image_source": "//cdn2.aznude.com/cg/queerasfolk/QueerasFolk01x02-CGKeitel-HD-01_largeCelebPage-4.jpg", "type": "video"}, {"link_to_media": "https://cdn2.aznude.com/cg/queerasfolk/cg_453173.jpg", "eid": null, "image_source": "https://cdn2.aznude.com/antibandit/cg/queerasfolk/thumb3_cg_453173.jpg", "type": "picture"}]}]}, {"actress_name": "Marcela Guirado", "birthplace": "Mexico", "hashtag": "nude", "celeb_img_url": "https://cdn2.aznude.com/biopic/aznceleb-4004335_biopic.jpg", "view_count": "776", "url": "https://aznude.com/view/celeb/m/marcelaguirado.html", "production_media_list": [{"type": "Series", "title": "LA NEGOCIADORA", "start_year": "2020", "end_year": null, "ongoing": false, "media_list": [{"link_to_media": "/azncdn/43ef7a7af66a4619a53d7ac126e4c992/43ef7a7af66a4619a53d7ac126e4c992-hi.html", "eid": "/embed/43ef7a7af66a4619a53d7ac126e4c992-hi.html", "image_source": "//cdn2.aznude.com/43ef7a7af66a4619a53d7ac126e4c992/43ef7a7af66a4619a53d7ac126e4c992-largeCelebPage-4.jpg", "type": "video"}, {"link_to_media": "https://cdn2.aznude.com/3780af33c0254e02ba7031a27b051193/3780af33c0254e02ba7031a27b051193.jpg", "eid": null, "image_source": "https://cdn2.aznude.com/antibandit/3780af33c0254e02ba7031a27b051193/thumb3_3780af33c0254e02ba7031a27b051193.jpg", "type": "picture"}, {"link_to_media": "https://cdn2.aznude.com/3c31bd550f9e4150ab4492858677bffe/3c31bd550f9e4150ab4492858677bffe.jpg", "eid": null, "image_source": "https://cdn2.aznude.com/antibandit/3c31bd550f9e4150ab4492858677bffe/thumb3_3c31bd550f9e4150ab4492858677bffe.jpg", "type": "picture"}, {"link_to_media": "https://cdn2.aznude.com/22f604bb527648c7b89d5f06b4f8359d/22f604bb527648c7b89d5f06b4f8359d.jpg", "eid": null, "image_source": "https://cdn2.aznude.com/antibandit/22f604bb527648c7b89d5f06b4f8359d/thumb3_22f604bb527648c7b89d5f06b4f8359d.jpg", "type": "picture"}, {"link_to_media": "https://cdn2.aznude.com/42af2205051545c9a3f2170b3f6d3e79/42af2205051545c9a3f2170b3f6d3e79.jpg", "eid": null, "image_source": "https://cdn2.aznude.com/antibandit/42af2205051545c9a3f2170b3f6d3e79/thumb3_42af2205051545c9a3f2170b3f6d3e79.jpg", "type": "picture"}, {"link_to_media": "https://cdn2.aznude.com/9c3c39cbcfd245858ce8ab3f83104fb5/9c3c39cbcfd245858ce8ab3f83104fb5.jpg", "eid": null, "image_source": "https://cdn2.aznude.com/antibandit/9c3c39cbcfd245858ce8ab3f83104fb5/thumb3_9c3c39cbcfd245858ce8ab3f83104fb5.jpg", "type": "picture"}, {"link_to_media": "https://cdn2.aznude.com/c07cad75ac7f4d4d9c01cc0558541814/c07cad75ac7f4d4d9c01cc0558541814.jpg", "eid": null, "image_source": "https://cdn2.aznude.com/antibandit/c07cad75ac7f4d4d9c01cc0558541814/thumb3_c07cad75ac7f4d4d9c01cc0558541814.jpg", "type": "picture"}, {"link_to_media": "https://cdn2.aznude.com/2313237a972a47a283093f4225d82d91/2313237a972a47a283093f4225d82d91.jpg", "eid": null, "image_source": "https://cdn2.aznude.com/antibandit/2313237a972a47a283093f4225d82d91/thumb3_2313237a972a47a283093f4225d82d91.jpg", "type": "picture"}, {"link_to_media": "https://cdn2.aznude.com/903d61343e3d40668990e14d6040656f/903d61343e3d40668990e14d6040656f.jpg", "eid": null, "image_source": "https://cdn2.aznude.com/antibandit/903d61343e3d40668990e14d6040656f/thumb3_903d61343e3d40668990e14d6040656f.jpg", "type": "picture"}, {"link_to_media": "https://cdn2.aznude.com/0992d1e3d03b4ec89a5fe3007459b3a1/0992d1e3d03b4ec89a5fe3007459b3a1.jpg", "eid": null, "image_source": "https://cdn2.aznude.com/antibandit/0992d1e3d03b4ec89a5fe3007459b3a1/thumb3_0992d1e3d03b4ec89a5fe3007459b3a1.jpg", "type": "picture"}]}, {"type": "Movie", "title": "ASI EN EL BARRIO COMO EN EL CIELO", "start_year": "2015", "end_year": null, "ongoing": false, "media_list": [{"link_to_media": "/azncdn/ec516adf32b64ea685b7919db0794bbb/ec516adf32b64ea685b7919db0794bbb-hd.html", "eid": "/embed/ec516adf32b64ea685b7919db0794bbb-hd.html", "image_source": "//cdn2.aznude.com/ec516adf32b64ea685b7919db0794bbb/ec516adf32b64ea685b7919db0794bbb-largeCelebPage-4.jpg", "type": "video"}, {"link_to_media": "https://cdn2.aznude.com/0e069a0e78e64b7da2bf0bcb7fa84361/0e069a0e78e64b7da2bf0bcb7fa84361.jpg", "eid": null, "image_source": "https://cdn2.aznude.com/antibandit/0e069a0e78e64b7da2bf0bcb7fa84361/thumb3_0e069a0e78e64b7da2bf0bcb7fa84361.jpg", "type": "picture"}, {"link_to_media": "https://cdn2.aznude.com/d583c45fc72d4bb79d31b7bdf9aaf937/d583c45fc72d4bb79d31b7bdf9aaf937.jpg", "eid": null, "image_source": "https://cdn2.aznude.com/antibandit/d583c45fc72d4bb79d31b7bdf9aaf937/thumb3_d583c45fc72d4bb79d31b7bdf9aaf937.jpg", "type": "picture"}, {"link_to_media": "https://cdn2.aznude.com/bc84a9fef3c2450aab82cce987c3066d/bc84a9fef3c2450aab82cce987c3066d.jpg", "eid": null, "image_source": "https://cdn2.aznude.com/antibandit/bc84a9fef3c2450aab82cce987c3066d/thumb3_bc84a9fef3c2450aab82cce987c3066d.jpg", "type": "picture"}]}, {"type": "Movie", "title": "SOY TU FAN", "start_year": "2010", "end_year": null, "ongoing": false, "media_list": [{"link_to_media": "/azncdn/2415f121cbed414789cd1b3a1c3a9395/2415f121cbed414789cd1b3a1c3a9395-hd.html", "eid": "/embed/2415f121cbed414789cd1b3a1c3a9395-hd.html", "image_source": "//cdn2.aznude.com/2415f121cbed414789cd1b3a1c3a9395/2415f121cbed414789cd1b3a1c3a9395-largeCelebPage-4.jpg", "type": "video"}, {"link_to_media": "https://cdn2.aznude.com/4febd820d24d4a598ffe98f3f6c774fd/4febd820d24d4a598ffe98f3f6c774fd.jpg", "eid": null, "image_source": "https://cdn2.aznude.com/antibandit/4febd820d24d4a598ffe98f3f6c774fd/thumb3_4febd820d24d4a598ffe98f3f6c774fd.jpg", "type": "picture"}, {"link_to_media": "https://cdn2.aznude.com/70a3c4eabda64b49abe1730dc5b6f498/70a3c4eabda64b49abe1730dc5b6f498.jpg", "eid": null, "image_source": "https://cdn2.aznude.com/antibandit/70a3c4eabda64b49abe1730dc5b6f498/thumb3_70a3c4eabda64b49abe1730dc5b6f498.jpg", "type": "picture"}, {"link_to_media": "https://cdn2.aznude.com/c317edcbc24647578ecfd38b88930b64/c317edcbc24647578ecfd38b88930b64.jpg", "eid": null, "image_source": "https://cdn2.aznude.com/antibandit/c317edcbc24647578ecfd38b88930b64/thumb3_c317edcbc24647578ecfd38b88930b64.jpg", "type": "picture"}, {"link_to_media": "https://cdn2.aznude.com/7831910832d344f990719b22f8c3dad4/7831910832d344f990719b22f8c3dad4.jpg", "eid": null, "image_source": "https://cdn2.aznude.com/antibandit/7831910832d344f990719b22f8c3dad4/thumb3_7831910832d344f990719b22f8c3dad4.jpg", "type": "picture"}]}]}, {"actress_name": "Tiina Mikkola", "birthplace": "Finland", "hashtag": "nude", "celeb_img_url": "https://cdn2.aznude.com/biopic/aznceleb-4006623_biopic.jpg", "view_count": "776", "url": "https://aznude.com/view/celeb/t/tiinamikkola.html", "production_media_list": [{"type": "Movie", "title": "BIG BROTHER SUOMI", "start_year": "2005", "end_year": null, "ongoing": false, "media_list": [{"link_to_media": "/azncdn/85cb4655c6424870aef52a29f3b360ba/85cb4655c6424870aef52a29f3b360ba-hi.html", "eid": "/embed/85cb4655c6424870aef52a29f3b360ba-hi.html", "image_source": "//cdn2.aznude.com/85cb4655c6424870aef52a29f3b360ba/85cb4655c6424870aef52a29f3b360ba-largeCelebPage-4.jpg", "type": "video"}, {"link_to_media": "https://cdn2.aznude.com/dba004e874914ff1a37ba9d5eea251c9/dba004e874914ff1a37ba9d5eea251c9.jpg", "eid": null, "image_source": "https://cdn2.aznude.com/antibandit/dba004e874914ff1a37ba9d5eea251c9/thumb3_dba004e874914ff1a37ba9d5eea251c9.jpg", "type": "picture"}, {"link_to_media": "https://cdn2.aznude.com/2510397df1a64b5998e6d6739f7c1e3d/2510397df1a64b5998e6d6739f7c1e3d.jpg", "eid": null, "image_source": "https://cdn2.aznude.com/antibandit/2510397df1a64b5998e6d6739f7c1e3d/thumb3_2510397df1a64b5998e6d6739f7c1e3d.jpg", "type": "picture"}, {"link_to_media": "https://cdn2.aznude.com/2f1db291b57245c08a7b8147d55c1dde/2f1db291b57245c08a7b8147d55c1dde.jpg", "eid": null, "image_source": "https://cdn2.aznude.com/antibandit/2f1db291b57245c08a7b8147d55c1dde/thumb3_2f1db291b57245c08a7b8147d55c1dde.jpg", "type": "picture"}, {"link_to_media": "https://cdn2.aznude.com/4cf143e76e99428d9527590d9cdd27be/4cf143e76e99428d9527590d9cdd27be.jpg", "eid": null, "image_source": "https://cdn2.aznude.com/antibandit/4cf143e76e99428d9527590d9cdd27be/thumb3_4cf143e76e99428d9527590d9cdd27be.jpg", "type": "picture"}, {"link_to_media": "https://cdn2.aznude.com/edf91921a79746b4bd90c4bd3a1e765f/edf91921a79746b4bd90c4bd3a1e765f.jpg", "eid": null, "image_source": "https://cdn2.aznude.com/antibandit/edf91921a79746b4bd90c4bd3a1e765f/thumb3_edf91921a79746b4bd90c4bd3a1e765f.jpg", "type": "picture"}]}]}, {"actress_name": "Emma Garcia", "birthplace": "Spain", "hashtag": "nude", "celeb_img_url": "https://cdn2.aznude.com/biopic/aznceleb-4010978_biopic.jpg", "view_count": "776", "url": "https://aznude.com/view/celeb/e/emmagarcia.html", "production_media_list": [{"type": "Story", "title": "EMMA GARCIA ACCIDENTAL UPSKIRT IN A TV SHOW", "start_year": "2023", "end_year": null, "ongoing": false, "media_list": []}]}, {"actress_name": "AnNa R.", "birthplace": "Germany", "hashtag": "nude", "celeb_img_url": "https://cdn2.aznude.com/biopic/aznceleb-4015439_biopic.jpg", "view_count": "776", "url": "https://aznude.com/view/celeb/a/annar.html", "production_media_list": [{"type": "Story", "title": "ANNA R. SEXY COLLECTION REVEALED AT BERLIN MUSIC FESTIVAL", "start_year": "2021", "end_year": null, "ongoing": false, "media_list": []}]}, {"actress_name": "Aleksandra Bulychyova", "birthplace": "Russia", "hashtag": "nude", "celeb_img_url": "https://cdn2.aznude.com/biopic/aznceleb-4016117_biopic.jpg", "view_count": "776", "url": "https://aznude.com/view/celeb/a/aleksandrabulychyova.html", "production_media_list": [{"type": "Series", "title": "THE SNOW QUEEN", "start_year": "2019", "end_year": null, "ongoing": false, "media_list": [{"link_to_media": "/azncdn/01fd904816b143c7ada35a9aacaaa402/01fd904816b143c7ada35a9aacaaa402-hd.html", "eid": "/embed/01fd904816b143c7ada35a9aacaaa402-hd.html", "image_source": "//cdn2.aznude.com/01fd904816b143c7ada35a9aacaaa402/01fd904816b143c7ada35a9aacaaa402-largeCelebPage-4.jpg", "type": "video"}, {"link_to_media": "https://cdn2.aznude.com/5d138053da774e88b0dce8b3f3a87794/5d138053da774e88b0dce8b3f3a87794.jpg", "eid": null, "image_source": "https://cdn2.aznude.com/antibandit/5d138053da774e88b0dce8b3f3a87794/thumb3_5d138053da774e88b0dce8b3f3a87794.jpg", "type": "picture"}, {"link_to_media": "https://cdn2.aznude.com/cff0adbfd68244f38ee7787a754be406/cff0adbfd68244f38ee7787a754be406.jpg", "eid": null, "image_source": "https://cdn2.aznude.com/antibandit/cff0adbfd68244f38ee7787a754be406/thumb3_cff0adbfd68244f38ee7787a754be406.jpg", "type": "picture"}, {"link_to_media": "https://cdn2.aznude.com/b4f1526816374148979371661ad69ca4/b4f1526816374148979371661ad69ca4.jpg", "eid": null, "image_source": "https://cdn2.aznude.com/antibandit/b4f1526816374148979371661ad69ca4/thumb3_b4f1526816374148979371661ad69ca4.jpg", "type": "picture"}, {"link_to_media": "https://cdn2.aznude.com/1d13eee3b3234b66930e2eb32f4f7d01/1d13eee3b3234b66930e2eb32f4f7d01.jpg", "eid": null, "image_source": "https://cdn2.aznude.com/antibandit/1d13eee3b3234b66930e2eb32f4f7d01/thumb3_1d13eee3b3234b66930e2eb32f4f7d01.jpg", "type": "picture"}, {"link_to_media": "https://cdn2.aznude.com/eb667623f3ae424882f8a10eea4647e0/eb667623f3ae424882f8a10eea4647e0.jpg", "eid": null, "image_source": "https://cdn2.aznude.com/antibandit/eb667623f3ae424882f8a10eea4647e0/thumb3_eb667623f3ae424882f8a10eea4647e0.jpg", "type": "picture"}, {"link_to_media": "https://cdn2.aznude.com/f9af1959f6d541d584332fc150ddc4c1/f9af1959f6d541d584332fc150ddc4c1.jpg", "eid": null, "image_source": "https://cdn2.aznude.com/antibandit/f9af1959f6d541d584332fc150ddc4c1/thumb3_f9af1959f6d541d584332fc150ddc4c1.jpg", "type": "picture"}]}]}, {"actress_name": "Yanina Zilly", "birthplace": "", "hashtag": "nude", "celeb_img_url": "https://cdn2.aznude.com/biopic/aznceleb-4016370_biopic.jpg", "view_count": "776", "url": "https://aznude.com/view/celeb/y/yaninazilly.html", "production_media_list": [{"type": "Movie", "title": "TELESHOW", "start_year": "2012", "end_year": null, "ongoing": false, "media_list": [{"link_to_media": "/azncdn/3c954c8a56f94afcb4851f4c5050df4c/3c954c8a56f94afcb4851f4c5050df4c-hd.html", "eid": "/embed/3c954c8a56f94afcb4851f4c5050df4c-hd.html", "image_source": "//cdn2.aznude.com/3c954c8a56f94afcb4851f4c5050df4c/3c954c8a56f94afcb4851f4c5050df4c-largeCelebPage-4.jpg", "type": "video"}, {"link_to_media": "https://cdn2.aznude.com/646e95ead48644dcba658d3747f706cf/646e95ead48644dcba658d3747f706cf.jpg", "eid": null, "image_source": "https://cdn2.aznude.com/antibandit/646e95ead48644dcba658d3747f706cf/thumb3_646e95ead48644dcba658d3747f706cf.jpg", "type": "picture"}, {"link_to_media": "https://cdn2.aznude.com/7954fd853ffc41fda740e8eef04130dc/7954fd853ffc41fda740e8eef04130dc.jpg", "eid": null, "image_source": "https://cdn2.aznude.com/antibandit/7954fd853ffc41fda740e8eef04130dc/thumb3_7954fd853ffc41fda740e8eef04130dc.jpg", "type": "picture"}, {"link_to_media": "https://cdn2.aznude.com/3209627c3b1d494c92365581df7e4400/3209627c3b1d494c92365581df7e4400.jpg", "eid": null, "image_source": "https://cdn2.aznude.com/antibandit/3209627c3b1d494c92365581df7e4400/thumb3_3209627c3b1d494c92365581df7e4400.jpg", "type": "picture"}, {"link_to_media": "https://cdn2.aznude.com/ea01a6b76e1846d2923ef25c2ba5dfde/ea01a6b76e1846d2923ef25c2ba5dfde.jpg", "eid": null, "image_source": "https://cdn2.aznude.com/antibandit/ea01a6b76e1846d2923ef25c2ba5dfde/thumb3_ea01a6b76e1846d2923ef25c2ba5dfde.jpg", "type": "picture"}, {"link_to_media": "https://cdn2.aznude.com/b853a9d797ba49ef80f6f773bbf4681a/b853a9d797ba49ef80f6f773bbf4681a.jpg", "eid": null, "image_source": "https://cdn2.aznude.com/antibandit/b853a9d797ba49ef80f6f773bbf4681a/thumb3_b853a9d797ba49ef80f6f773bbf4681a.jpg", "type": "picture"}, {"link_to_media": "https://cdn2.aznude.com/323ff1da716649be8e17a7753991c0ec/323ff1da716649be8e17a7753991c0ec.jpg", "eid": null, "image_source": "https://cdn2.aznude.com/antibandit/323ff1da716649be8e17a7753991c0ec/thumb3_323ff1da716649be8e17a7753991c0ec.jpg", "type": "picture"}, {"link_to_media": "https://cdn2.aznude.com/ed7e5eb4607c4b3eb0b1eda8564b1ac5/ed7e5eb4607c4b3eb0b1eda8564b1ac5.jpg", "eid": null, "image_source": "https://cdn2.aznude.com/antibandit/ed7e5eb4607c4b3eb0b1eda8564b1ac5/thumb3_ed7e5eb4607c4b3eb0b1eda8564b1ac5.jpg", "type": "picture"}, {"link_to_media": "https://cdn2.aznude.com/78803d64c9f94b29b20a24c0dd8a2a41/78803d64c9f94b29b20a24c0dd8a2a41.jpg", "eid": null, "image_source": "https://cdn2.aznude.com/antibandit/78803d64c9f94b29b20a24c0dd8a2a41/thumb3_78803d64c9f94b29b20a24c0dd8a2a41.jpg", "type": "picture"}]}, {"type": "Series", "title": "INTRUSOS EN EL ESPECTACULO", "start_year": "2001", "end_year": null, "ongoing": false, "media_list": [{"link_to_media": "/azncdn/b4d70fde9fbe4a409fe3aeba946db0be/b4d70fde9fbe4a409fe3aeba946db0be-hi.html", "eid": "/embed/b4d70fde9fbe4a409fe3aeba946db0be-hi.html", "image_source": "//cdn2.aznude.com/b4d70fde9fbe4a409fe3aeba946db0be/b4d70fde9fbe4a409fe3aeba946db0be-largeCelebPage-4.jpg", "type": "video"}, {"link_to_media": "https://cdn2.aznude.com/60cec0c0b1184a948c6d1cf6dc8f7e51/60cec0c0b1184a948c6d1cf6dc8f7e51.jpg", "eid": null, "image_source": "https://cdn2.aznude.com/antibandit/60cec0c0b1184a948c6d1cf6dc8f7e51/thumb3_60cec0c0b1184a948c6d1cf6dc8f7e51.jpg", "type": "picture"}, {"link_to_media": "https://cdn2.aznude.com/2fa45e7d63be46b1b2450d10d744f3b5/2fa45e7d63be46b1b2450d10d744f3b5.jpg", "eid": null, "image_source": "https://cdn2.aznude.com/antibandit/2fa45e7d63be46b1b2450d10d744f3b5/thumb3_2fa45e7d63be46b1b2450d10d744f3b5.jpg", "type": "picture"}, {"link_to_media": "https://cdn2.aznude.com/1a0b73af0cad44679d2737de3a4ca983/1a0b73af0cad44679d2737de3a4ca983.jpg", "eid": null, "image_source": "https://cdn2.aznude.com/antibandit/1a0b73af0cad44679d2737de3a4ca983/thumb3_1a0b73af0cad44679d2737de3a4ca983.jpg", "type": "picture"}]}, {"type": "Movie", "title": "IMITACIONES PELIGROSAS", "start_year": "1999", "end_year": null, "ongoing": false, "media_list": [{"link_to_media": "/azncdn/4db7daede1b54014989e4538dc872567/4db7daede1b54014989e4538dc872567-hi.html", "eid": "/embed/4db7daede1b54014989e4538dc872567-hi.html", "image_source": "//cdn2.aznude.com/4db7daede1b54014989e4538dc872567/4db7daede1b54014989e4538dc872567-largeCelebPage-4.jpg", "type": "video"}, {"link_to_media": "https://cdn2.aznude.com/9537c5cd87194ba180496f9e8e59b9a4/9537c5cd87194ba180496f9e8e59b9a4.jpg", "eid": null, "image_source": "https://cdn2.aznude.com/antibandit/9537c5cd87194ba180496f9e8e59b9a4/thumb3_9537c5cd87194ba180496f9e8e59b9a4.jpg", "type": "picture"}, {"link_to_media": "https://cdn2.aznude.com/b4e620df197848c6b711efa37c8b9469/b4e620df197848c6b711efa37c8b9469.jpg", "eid": null, "image_source": "https://cdn2.aznude.com/antibandit/b4e620df197848c6b711efa37c8b9469/thumb3_b4e620df197848c6b711efa37c8b9469.jpg", "type": "picture"}, {"link_to_media": "https://cdn2.aznude.com/56a0e47641624c40bdab08b34c159e86/56a0e47641624c40bdab08b34c159e86.jpg", "eid": null, "image_source": "https://cdn2.aznude.com/antibandit/56a0e47641624c40bdab08b34c159e86/thumb3_56a0e47641624c40bdab08b34c159e86.jpg", "type": "picture"}, {"link_to_media": "https://cdn2.aznude.com/203930f732814659addfc94c8dc91471/203930f732814659addfc94c8dc91471.jpg", "eid": null, "image_source": "https://cdn2.aznude.com/antibandit/203930f732814659addfc94c8dc91471/thumb3_203930f732814659addfc94c8dc91471.jpg", "type": "picture"}, {"link_to_media": "https://cdn2.aznude.com/3667e73138414801961772d15f2ce45e/3667e73138414801961772d15f2ce45e.jpg", "eid": null, "image_source": "https://cdn2.aznude.com/antibandit/3667e73138414801961772d15f2ce45e/thumb3_3667e73138414801961772d15f2ce45e.jpg", "type": "picture"}, {"link_to_media": "https://cdn2.aznude.com/f1f0d8528d0746848e5e5462513ce77c/f1f0d8528d0746848e5e5462513ce77c.jpg", "eid": null, "image_source": "https://cdn2.aznude.com/antibandit/f1f0d8528d0746848e5e5462513ce77c/thumb3_f1f0d8528d0746848e5e5462513ce77c.jpg", "type": "picture"}, {"link_to_media": "https://cdn2.aznude.com/4ea0e64052fc4adea24baa4e5d2cdf40/4ea0e64052fc4adea24baa4e5d2cdf40.jpg", "eid": null, "image_source": "https://cdn2.aznude.com/antibandit/4ea0e64052fc4adea24baa4e5d2cdf40/thumb3_4ea0e64052fc4adea24baa4e5d2cdf40.jpg", "type": "picture"}, {"link_to_media": "https://cdn2.aznude.com/b36d368277b4436d8a4482d9766ee5bb/b36d368277b4436d8a4482d9766ee5bb.jpg", "eid": null, "image_source": "https://cdn2.aznude.com/antibandit/b36d368277b4436d8a4482d9766ee5bb/thumb3_b36d368277b4436d8a4482d9766ee5bb.jpg", "type": "picture"}, {"link_to_media": "https://cdn2.aznude.com/876ee373af0c4fb0afd7a81379d5b6a7/876ee373af0c4fb0afd7a81379d5b6a7.jpg", "eid": null, "image_source": "https://cdn2.aznude.com/antibandit/876ee373af0c4fb0afd7a81379d5b6a7/thumb3_876ee373af0c4fb0afd7a81379d5b6a7.jpg", "type": "picture"}, {"link_to_media": "https://cdn2.aznude.com/22039a8b2a3e4c0ba07280d2f902db25/22039a8b2a3e4c0ba07280d2f902db25.jpg", "eid": null, "image_source": "https://cdn2.aznude.com/antibandit/22039a8b2a3e4c0ba07280d2f902db25/thumb3_22039a8b2a3e4c0ba07280d2f902db25.jpg", "type": "picture"}]}, {"type": "Series", "title": "VERSUS", "start_year": "1998", "end_year": null, "ongoing": false, "media_list": [{"link_to_media": "/azncdn/eaff4eb0e6bc4a79a3a13b59256fe975/eaff4eb0e6bc4a79a3a13b59256fe975-hi.html", "eid": "/embed/eaff4eb0e6bc4a79a3a13b59256fe975-hi.html", "image_source": "//cdn2.aznude.com/eaff4eb0e6bc4a79a3a13b59256fe975/eaff4eb0e6bc4a79a3a13b59256fe975-largeCelebPage-4.jpg", "type": "video"}, {"link_to_media": "https://cdn2.aznude.com/d38c6e32746c4d508e8e28deff77dd34/d38c6e32746c4d508e8e28deff77dd34.jpg", "eid": null, "image_source": "https://cdn2.aznude.com/antibandit/d38c6e32746c4d508e8e28deff77dd34/thumb3_d38c6e32746c4d508e8e28deff77dd34.jpg", "type": "picture"}, {"link_to_media": "https://cdn2.aznude.com/ad653b7de20c4c5394b231aeda1e46f4/ad653b7de20c4c5394b231aeda1e46f4.jpg", "eid": null, "image_source": "https://cdn2.aznude.com/antibandit/ad653b7de20c4c5394b231aeda1e46f4/thumb3_ad653b7de20c4c5394b231aeda1e46f4.jpg", "type": "picture"}, {"link_to_media": "https://cdn2.aznude.com/b1b5d7cb7776427e83d67cece49a90fd/b1b5d7cb7776427e83d67cece49a90fd.jpg", "eid": null, "image_source": "https://cdn2.aznude.com/antibandit/b1b5d7cb7776427e83d67cece49a90fd/thumb3_b1b5d7cb7776427e83d67cece49a90fd.jpg", "type": "picture"}, {"link_to_media": "https://cdn2.aznude.com/8ac923afe9ec4421be49a5e5e23a4ed3/8ac923afe9ec4421be49a5e5e23a4ed3.jpg", "eid": null, "image_source": "https://cdn2.aznude.com/antibandit/8ac923afe9ec4421be49a5e5e23a4ed3/thumb3_8ac923afe9ec4421be49a5e5e23a4ed3.jpg", "type": "picture"}, {"link_to_media": "https://cdn2.aznude.com/8a6a0721af8b4650a0c202b2020d394f/8a6a0721af8b4650a0c202b2020d394f.jpg", "eid": null, "image_source": "https://cdn2.aznude.com/antibandit/8a6a0721af8b4650a0c202b2020d394f/thumb3_8a6a0721af8b4650a0c202b2020d394f.jpg", "type": "picture"}, {"link_to_media": "https://cdn2.aznude.com/879c0baac09640a7b9d6f154735ee46a/879c0baac09640a7b9d6f154735ee46a.jpg", "eid": null, "image_source": "https://cdn2.aznude.com/antibandit/879c0baac09640a7b9d6f154735ee46a/thumb3_879c0baac09640a7b9d6f154735ee46a.jpg", "type": "picture"}, {"link_to_media": "https://cdn2.aznude.com/e055de4460f94c13ab8bd2e88fd706f8/e055de4460f94c13ab8bd2e88fd706f8.jpg", "eid": null, "image_source": "https://cdn2.aznude.com/antibandit/e055de4460f94c13ab8bd2e88fd706f8/thumb3_e055de4460f94c13ab8bd2e88fd706f8.jpg", "type": "picture"}, {"link_to_media": "https://cdn2.aznude.com/d213809ed7aa471582587c60d40ccac0/d213809ed7aa471582587c60d40ccac0.jpg", "eid": null, "image_source": "https://cdn2.aznude.com/antibandit/d213809ed7aa471582587c60d40ccac0/thumb3_d213809ed7aa471582587c60d40ccac0.jpg", "type": "picture"}]}, {"type": "Series", "title": "ROMPEPORTONES", "start_year": "1998", "end_year": null, "ongoing": false, "media_list": [{"link_to_media": "/azncdn/52b3769f96ca481ead8e0b071a79e424/52b3769f96ca481ead8e0b071a79e424-hd.html", "eid": "/embed/52b3769f96ca481ead8e0b071a79e424-hd.html", "image_source": "//cdn2.aznude.com/52b3769f96ca481ead8e0b071a79e424/52b3769f96ca481ead8e0b071a79e424-largeCelebPage-4.jpg", "type": "video"}, {"link_to_media": "https://cdn2.aznude.com/460ada751bb94b9ea53b074005b9c2bc/460ada751bb94b9ea53b074005b9c2bc.jpg", "eid": null, "image_source": "https://cdn2.aznude.com/antibandit/460ada751bb94b9ea53b074005b9c2bc/thumb3_460ada751bb94b9ea53b074005b9c2bc.jpg", "type": "picture"}, {"link_to_media": "https://cdn2.aznude.com/2c81af3e4aef48818040d43d11b8e9e9/2c81af3e4aef48818040d43d11b8e9e9.jpg", "eid": null, "image_source": "https://cdn2.aznude.com/antibandit/2c81af3e4aef48818040d43d11b8e9e9/thumb3_2c81af3e4aef48818040d43d11b8e9e9.jpg", "type": "picture"}, {"link_to_media": "https://cdn2.aznude.com/fbda56a0b063486eb9d13367f08ea13b/fbda56a0b063486eb9d13367f08ea13b.jpg", "eid": null, "image_source": "https://cdn2.aznude.com/antibandit/fbda56a0b063486eb9d13367f08ea13b/thumb3_fbda56a0b063486eb9d13367f08ea13b.jpg", "type": "picture"}, {"link_to_media": "https://cdn2.aznude.com/a985936cd4e54f0a98e594462b85a474/a985936cd4e54f0a98e594462b85a474.jpg", "eid": null, "image_source": "https://cdn2.aznude.com/antibandit/a985936cd4e54f0a98e594462b85a474/thumb3_a985936cd4e54f0a98e594462b85a474.jpg", "type": "picture"}, {"link_to_media": "https://cdn2.aznude.com/165f891f54f8482f8b37030ef6056969/165f891f54f8482f8b37030ef6056969.jpg", "eid": null, "image_source": "https://cdn2.aznude.com/antibandit/165f891f54f8482f8b37030ef6056969/thumb3_165f891f54f8482f8b37030ef6056969.jpg", "type": "picture"}, {"link_to_media": "https://cdn2.aznude.com/0f935ce2d4ab44d2b2be676ca5e56083/0f935ce2d4ab44d2b2be676ca5e56083.jpg", "eid": null, "image_source": "https://cdn2.aznude.com/antibandit/0f935ce2d4ab44d2b2be676ca5e56083/thumb3_0f935ce2d4ab44d2b2be676ca5e56083.jpg", "type": "picture"}, {"link_to_media": "https://cdn2.aznude.com/1525e72e349e4d7a8537269ee2dd47e9/1525e72e349e4d7a8537269ee2dd47e9.jpg", "eid": null, "image_source": "https://cdn2.aznude.com/antibandit/1525e72e349e4d7a8537269ee2dd47e9/thumb3_1525e72e349e4d7a8537269ee2dd47e9.jpg", "type": "picture"}, {"link_to_media": "https://cdn2.aznude.com/2ff1b58213ec4a12b57e49d68d8c55c4/2ff1b58213ec4a12b57e49d68d8c55c4.jpg", "eid": null, "image_source": "https://cdn2.aznude.com/antibandit/2ff1b58213ec4a12b57e49d68d8c55c4/thumb3_2ff1b58213ec4a12b57e49d68d8c55c4.jpg", "type": "picture"}, {"link_to_media": "https://cdn2.aznude.com/5ed02579eef240da9e794abb74cabefe/5ed02579eef240da9e794abb74cabefe.jpg", "eid": null, "image_source": "https://cdn2.aznude.com/antibandit/5ed02579eef240da9e794abb74cabefe/thumb3_5ed02579eef240da9e794abb74cabefe.jpg", "type": "picture"}]}, {"type": "Series", "title": "VIDEOMATCH", "start_year": "1990", "end_year": null, "ongoing": false, "media_list": [{"link_to_media": "/azncdn/031c7d49328346d3a4504d8cf75c923d/031c7d49328346d3a4504d8cf75c923d-hd.html", "eid": "/embed/031c7d49328346d3a4504d8cf75c923d-hd.html", "image_source": "//cdn2.aznude.com/031c7d49328346d3a4504d8cf75c923d/031c7d49328346d3a4504d8cf75c923d-largeCelebPage-4.jpg", "type": "video"}, {"link_to_media": "https://cdn2.aznude.com/a14744b9f4204de88b536124c0fa9e12/a14744b9f4204de88b536124c0fa9e12.jpg", "eid": null, "image_source": "https://cdn2.aznude.com/antibandit/a14744b9f4204de88b536124c0fa9e12/thumb3_a14744b9f4204de88b536124c0fa9e12.jpg", "type": "picture"}, {"link_to_media": "https://cdn2.aznude.com/1c4bbcd351c84d89b8b7984794710749/1c4bbcd351c84d89b8b7984794710749.jpg", "eid": null, "image_source": "https://cdn2.aznude.com/antibandit/1c4bbcd351c84d89b8b7984794710749/thumb3_1c4bbcd351c84d89b8b7984794710749.jpg", "type": "picture"}, {"link_to_media": "https://cdn2.aznude.com/edbdb4c251d549ffa0a69a1c9373f5d6/edbdb4c251d549ffa0a69a1c9373f5d6.jpg", "eid": null, "image_source": "https://cdn2.aznude.com/antibandit/edbdb4c251d549ffa0a69a1c9373f5d6/thumb3_edbdb4c251d549ffa0a69a1c9373f5d6.jpg", "type": "picture"}, {"link_to_media": "https://cdn2.aznude.com/8c2dfdae9f88462ebc7358da84d56aed/8c2dfdae9f88462ebc7358da84d56aed.jpg", "eid": null, "image_source": "https://cdn2.aznude.com/antibandit/8c2dfdae9f88462ebc7358da84d56aed/thumb3_8c2dfdae9f88462ebc7358da84d56aed.jpg", "type": "picture"}, {"link_to_media": "https://cdn2.aznude.com/9f2ec553ef3d4ec98f79c6154a3dfcc7/9f2ec553ef3d4ec98f79c6154a3dfcc7.jpg", "eid": null, "image_source": "https://cdn2.aznude.com/antibandit/9f2ec553ef3d4ec98f79c6154a3dfcc7/thumb3_9f2ec553ef3d4ec98f79c6154a3dfcc7.jpg", "type": "picture"}, {"link_to_media": "https://cdn2.aznude.com/69b0279a5cab43af845a67a958dbb0c7/69b0279a5cab43af845a67a958dbb0c7.jpg", "eid": null, "image_source": "https://cdn2.aznude.com/antibandit/69b0279a5cab43af845a67a958dbb0c7/thumb3_69b0279a5cab43af845a67a958dbb0c7.jpg", "type": "picture"}, {"link_to_media": "https://cdn2.aznude.com/6a96d988ad0f4d57ab8152818acaefe5/6a96d988ad0f4d57ab8152818acaefe5.jpg", "eid": null, "image_source": "https://cdn2.aznude.com/antibandit/6a96d988ad0f4d57ab8152818acaefe5/thumb3_6a96d988ad0f4d57ab8152818acaefe5.jpg", "type": "picture"}, {"link_to_media": "https://cdn2.aznude.com/d3375b2a4ff54f7aac3bf977379d56dc/d3375b2a4ff54f7aac3bf977379d56dc.jpg", "eid": null, "image_source": "https://cdn2.aznude.com/antibandit/d3375b2a4ff54f7aac3bf977379d56dc/thumb3_d3375b2a4ff54f7aac3bf977379d56dc.jpg", "type": "picture"}]}]}, {"actress_name": "Purple Pam Shelby", "birthplace": "", "hashtag": "nude", "celeb_img_url": "https://cdn2.aznude.com/biopic/96946_biopic.jpg", "view_count": "774", "url": "https://aznude.com/view/celeb/p/purplepamshelby.html", "production_media_list": []}, {"actress_name": "Katerina Kornova", "birthplace": "Czech Republic", "hashtag": "nude", "celeb_img_url": "https://cdn2.aznude.com/biopic/aznceleb-4006148_biopic.jpg", "view_count": "774", "url": "https://aznude.com/view/celeb/k/katerinakornova.html", "production_media_list": [{"type": "Movie", "title": "CHAINED HEAT III: NO HOLDS BARRED", "start_year": "1998", "end_year": null, "ongoing": false, "media_list": [{"link_to_media": "/azncdn/9a4dcafe3cca40bfa40f7c8d462ac4a9/9a4dcafe3cca40bfa40f7c8d462ac4a9-hi.html", "eid": "/embed/9a4dcafe3cca40bfa40f7c8d462ac4a9-hi.html", "image_source": "//cdn2.aznude.com/9a4dcafe3cca40bfa40f7c8d462ac4a9/9a4dcafe3cca40bfa40f7c8d462ac4a9-largeCelebPage-4.jpg", "type": "video"}, {"link_to_media": "https://cdn2.aznude.com/3ef3e7ac14794b40aab3a2fae6cda52e/3ef3e7ac14794b40aab3a2fae6cda52e.jpg", "eid": null, "image_source": "https://cdn2.aznude.com/antibandit/3ef3e7ac14794b40aab3a2fae6cda52e/thumb3_3ef3e7ac14794b40aab3a2fae6cda52e.jpg", "type": "picture"}, {"link_to_media": "https://cdn2.aznude.com/206fe98df0ef4886aa66775135640e8c/206fe98df0ef4886aa66775135640e8c.jpg", "eid": null, "image_source": "https://cdn2.aznude.com/antibandit/206fe98df0ef4886aa66775135640e8c/thumb3_206fe98df0ef4886aa66775135640e8c.jpg", "type": "picture"}, {"link_to_media": "https://cdn2.aznude.com/736afeb1baae488d9eb97209c053870c/736afeb1baae488d9eb97209c053870c.jpg", "eid": null, "image_source": "https://cdn2.aznude.com/antibandit/736afeb1baae488d9eb97209c053870c/thumb3_736afeb1baae488d9eb97209c053870c.jpg", "type": "picture"}, {"link_to_media": "https://cdn2.aznude.com/6677332f9c194434af31685f8a06ca59/6677332f9c194434af31685f8a06ca59.jpg", "eid": null, "image_source": "https://cdn2.aznude.com/antibandit/6677332f9c194434af31685f8a06ca59/thumb3_6677332f9c194434af31685f8a06ca59.jpg", "type": "picture"}, {"link_to_media": "https://cdn2.aznude.com/72d48256335f4eefb87678cceea2a0bf/72d48256335f4eefb87678cceea2a0bf.jpg", "eid": null, "image_source": "https://cdn2.aznude.com/antibandit/72d48256335f4eefb87678cceea2a0bf/thumb3_72d48256335f4eefb87678cceea2a0bf.jpg", "type": "picture"}, {"link_to_media": "https://cdn2.aznude.com/07f96152a06f4481902fd1ecfe8edb11/07f96152a06f4481902fd1ecfe8edb11.jpg", "eid": null, "image_source": "https://cdn2.aznude.com/antibandit/07f96152a06f4481902fd1ecfe8edb11/thumb3_07f96152a06f4481902fd1ecfe8edb11.jpg", "type": "picture"}, {"link_to_media": "https://cdn2.aznude.com/f48a802e524d45469cbe368289635c89/f48a802e524d45469cbe368289635c89.jpg", "eid": null, "image_source": "https://cdn2.aznude.com/antibandit/f48a802e524d45469cbe368289635c89/thumb3_f48a802e524d45469cbe368289635c89.jpg", "type": "picture"}, {"link_to_media": "https://cdn2.aznude.com/58cf56b555f043eab39818987357db9f/58cf56b555f043eab39818987357db9f.jpg", "eid": null, "image_source": "https://cdn2.aznude.com/antibandit/58cf56b555f043eab39818987357db9f/thumb3_58cf56b555f043eab39818987357db9f.jpg", "type": "picture"}, {"link_to_media": "https://cdn2.aznude.com/04dac236b7324842a7ed0f20a12c7cdb/04dac236b7324842a7ed0f20a12c7cdb.jpg", "eid": null, "image_source": "https://cdn2.aznude.com/antibandit/04dac236b7324842a7ed0f20a12c7cdb/thumb3_04dac236b7324842a7ed0f20a12c7cdb.jpg", "type": "picture"}, {"link_to_media": "https://cdn2.aznude.com/b28cd89036924fa39e5e96dafb75be07/b28cd89036924fa39e5e96dafb75be07.jpg", "eid": null, "image_source": "https://cdn2.aznude.com/antibandit/b28cd89036924fa39e5e96dafb75be07/thumb3_b28cd89036924fa39e5e96dafb75be07.jpg", "type": "picture"}, {"link_to_media": "https://cdn2.aznude.com/cfc5640d87e443fe97d351253b02de6c/cfc5640d87e443fe97d351253b02de6c.jpg", "eid": null, "image_source": "https://cdn2.aznude.com/antibandit/cfc5640d87e443fe97d351253b02de6c/thumb3_cfc5640d87e443fe97d351253b02de6c.jpg", "type": "picture"}, {"link_to_media": "https://cdn2.aznude.com/d925365af4194a928d6f62b1cb2c6b87/d925365af4194a928d6f62b1cb2c6b87.jpg", "eid": null, "image_source": "https://cdn2.aznude.com/antibandit/d925365af4194a928d6f62b1cb2c6b87/thumb3_d925365af4194a928d6f62b1cb2c6b87.jpg", "type": "picture"}, {"link_to_media": "https://cdn2.aznude.com/ad5c13a774b14b69ad1954cbbb9342da/ad5c13a774b14b69ad1954cbbb9342da.jpg", "eid": null, "image_source": "https://cdn2.aznude.com/antibandit/ad5c13a774b14b69ad1954cbbb9342da/thumb3_ad5c13a774b14b69ad1954cbbb9342da.jpg", "type": "picture"}, {"link_to_media": "https://cdn2.aznude.com/9af4b7f6fec84b56add30fd3b8ad5cea/9af4b7f6fec84b56add30fd3b8ad5cea.jpg", "eid": null, "image_source": "https://cdn2.aznude.com/antibandit/9af4b7f6fec84b56add30fd3b8ad5cea/thumb3_9af4b7f6fec84b56add30fd3b8ad5cea.jpg", "type": "picture"}]}, {"type": "Movie", "title": "PLAYGIRLS", "start_year": "1995", "end_year": null, "ongoing": false, "media_list": [{"link_to_media": "/azncdn/8c73788805e94d748fda39e36034c65e/8c73788805e94d748fda39e36034c65e-hi.html", "eid": "/embed/8c73788805e94d748fda39e36034c65e-hi.html", "image_source": "//cdn2.aznude.com/8c73788805e94d748fda39e36034c65e/8c73788805e94d748fda39e36034c65e-largeCelebPage-4.jpg", "type": "video"}, {"link_to_media": "https://cdn2.aznude.com/53d6b47c658b45feb9717e4e7e303774/53d6b47c658b45feb9717e4e7e303774.jpg", "eid": null, "image_source": "https://cdn2.aznude.com/antibandit/53d6b47c658b45feb9717e4e7e303774/thumb3_53d6b47c658b45feb9717e4e7e303774.jpg", "type": "picture"}, {"link_to_media": "https://cdn2.aznude.com/0b1b612ba21146e8828b14027a9297ec/0b1b612ba21146e8828b14027a9297ec.jpg", "eid": null, "image_source": "https://cdn2.aznude.com/antibandit/0b1b612ba21146e8828b14027a9297ec/thumb3_0b1b612ba21146e8828b14027a9297ec.jpg", "type": "picture"}, {"link_to_media": "https://cdn2.aznude.com/e590b09ec18d4d539592172a9ff8a4c0/e590b09ec18d4d539592172a9ff8a4c0.jpg", "eid": null, "image_source": "https://cdn2.aznude.com/antibandit/e590b09ec18d4d539592172a9ff8a4c0/thumb3_e590b09ec18d4d539592172a9ff8a4c0.jpg", "type": "picture"}]}, {"type": "Movie", "title": "SWEDISH PACKAGE HOLIDAY", "start_year": "1989", "end_year": null, "ongoing": false, "media_list": [{"link_to_media": "/azncdn/29085f6eb1764cec9b923db47ff2eef3/29085f6eb1764cec9b923db47ff2eef3-hi.html", "eid": "/embed/29085f6eb1764cec9b923db47ff2eef3-hi.html", "image_source": "//cdn2.aznude.com/29085f6eb1764cec9b923db47ff2eef3/29085f6eb1764cec9b923db47ff2eef3-largeCelebPage-4.jpg", "type": "video"}, {"link_to_media": "https://cdn2.aznude.com/cf72ae3c87cf4770adbdd84f69052963/cf72ae3c87cf4770adbdd84f69052963.jpg", "eid": null, "image_source": "https://cdn2.aznude.com/antibandit/cf72ae3c87cf4770adbdd84f69052963/thumb3_cf72ae3c87cf4770adbdd84f69052963.jpg", "type": "picture"}, {"link_to_media": "https://cdn2.aznude.com/9ff2dfdd7426468caa19bc1484be62af/9ff2dfdd7426468caa19bc1484be62af.jpg", "eid": null, "image_source": "https://cdn2.aznude.com/antibandit/9ff2dfdd7426468caa19bc1484be62af/thumb3_9ff2dfdd7426468caa19bc1484be62af.jpg", "type": "picture"}, {"link_to_media": "https://cdn2.aznude.com/bdfaf182d20041208dc5f1215212974b/bdfaf182d20041208dc5f1215212974b.jpg", "eid": null, "image_source": "https://cdn2.aznude.com/antibandit/bdfaf182d20041208dc5f1215212974b/thumb3_bdfaf182d20041208dc5f1215212974b.jpg", "type": "picture"}]}]}, {"actress_name": "Benzino Fiance Althea", "birthplace": "", "hashtag": "nude", "celeb_img_url": "https://cdn2.aznude.com/biopic/story_celeb_1549322056-779626822.jpg", "view_count": "774", "url": "https://aznude.com/view/celeb/b/benzinofiancealthea.html", "production_media_list": [{"type": "Story", "title": "ALTHEA BENZINO RARE NUDE PHOTOS", "start_year": "2014", "end_year": null, "ongoing": false, "media_list": []}]}, {"actress_name": "Alek Wek", "birthplace": "", "hashtag": "nude", "celeb_img_url": "https://cdn2.aznude.com/biopic/story_celeb_1579475671-619557886.jpg", "view_count": "774", "url": "https://aznude.com/view/celeb/a/alekwek.html", "production_media_list": [{"type": "Story", "title": "ALEK WEK V MAGAZINE 2020 NUDE PHOTOS", "start_year": "2020", "end_year": null, "ongoing": false, "media_list": []}]}]